Workbook
Name List_GL: OFFSET(Lists!$A$2,0,0,MAX(1,COUNTA(Lists!$A:$A)-1),1)
Name List_Source: OFFSET(Lists!$B$2,0,0,MAX(1,COUNTA(Lists!$B:$B)-1),1)

Sheet Dashboard
A1: GL vs Source Reconciliation Dashboard
A3: Filters
A4: GL Account
A5: Source Account
A6: Date From (Posting)
A7: Date To (Posting)
A9: Effective Criteria (do not edit)
A10: GL Criteria | B10: =IF(B4="", "*", B4) -> *
A11: Source Criteria | B11: =IF(B5="", "*", B5) -> *
A12: Date From Eff | B12: =IF(B6="", DATE(1900,1,1), B6) -> 1
A13: Date To Eff | B13: =IF(B7="", DATE(9999,12,31), B7) -> 2958465
A15: Counts by Status (respects filters)
A16: Status | B16: Count
A17: EXACT_MATCH | B17: =COUNTIFS(tblModel[status],A17,tblModel[gl_account],$B$10,tblModel[source_account],$B$11,tblModel[posting_date],">="&$B$12,tblModel[posting_date],"<="&$B$13) -> 212
A18: NEAR_MATCH | B18: =COUNTIFS(tblModel[status],A18,tblModel[gl_account],$B$10,tblModel[source_account],$B$11,tblModel[posting_date],">="&$B$12,tblModel[posting_date],"<="&$B$13) -> 49
A19: MAPPING_ISSUE | B19: =COUNTIFS(tblModel[status],A19,tblModel[gl_account],$B$10,tblModel[source_account],$B$11,tblModel[posting_date],">="&$B$12,tblModel[posting_date],"<="&$B$13) -> 0
A20: MISMATCH | B20: =COUNTIFS(tblModel[status],A20,tblModel[gl_account],$B$10,tblModel[source_account],$B$11,tblModel[posting_date],">="&$B$12,tblModel[posting_date],"<="&$B$13) -> 39
A21: UNMATCHED_A | B21: =COUNTIFS(tblModel[status],A21,tblModel[gl_account],$B$10,tblModel[source_account],$B$11,tblModel[posting_date],">="&$B$12,tblModel[posting_date],"<="&$B$13) -> 0
A22: UNMATCHED_B | B22: =COUNTIFS(tblModel[status],A22,tblModel[gl_account],$B$10,tblModel[source_account],$B$11,tblModel[posting_date],">="&$B$12,tblModel[posting_date],"<="&$B$13) -> 0
A25: Exceptions by GL (MISMATCH + UNMATCHED_A)
A26: GL Account | B26: Exceptions
A27: =INDEX(Lists!$A:$A,2) -> 1000 | B27: =COUNTIFS(tblModel[status],"MISMATCH",tblModel[gl_account],A27,tblModel[gl_account],$B$10,tblModel[source_account],$B$11,tblModel[posting_date],">="&$B$12,tblModel[posting_date],"<="&$B$13)+COUNTIFS(tblModel[status],"UNMATCHED_A",tblModel[gl_account],A27,tblModel[gl_account],$B$10,tblModel[source_account],$B$11,tblModel[posting_date],">="&$B$12,tblModel[posting_date],"<="&$B$13) -> 8
A28: =INDEX(Lists!$A:$A,3) -> 1100 | B28: =COUNTIFS(tblModel[status],"MISMATCH",tblModel[gl_account],A28,tblModel[gl_account],$B$10,tblModel[source_account],$B$11,tblModel[posting_date],">="&$B$12,tblModel[posting_date],"<="&$B$13)+COUNTIFS(tblModel[status],"UNMATCHED_A",tblModel[gl_account],A28,tblModel[gl_account],$B$10,tblModel[source_account],$B$11,tblModel[posting_date],">="&$B$12,tblModel[posting_date],"<="&$B$13) -> 6
A29: =INDEX(Lists!$A:$A,4) -> 1200 | B29: =COUNTIFS(tblModel[status],"MISMATCH",tblModel[gl_account],A29,tblModel[gl_account],$B$10,tblModel[source_account],$B$11,tblModel[posting_date],">="&$B$12,tblModel[posting_date],"<="&$B$13)+COUNTIFS(tblModel[status],"UNMATCHED_A",tblModel[gl_account],A29,tblModel[gl_account],$B$10,tblModel[source_account],$B$11,tblModel[posting_date],">="&$B$12,tblModel[posting_date],"<="&$B$13) -> 0
A30: =INDEX(Lists!$A:$A,5) -> 2000 | B30: =COUNTIFS(tblModel[status],"MISMATCH",tblModel[gl_account],A30,tblModel[gl_account],$B$10,tblModel[source_account],$B$11,tblModel[posting_date],">="&$B$12,tblModel[posting_date],"<="&$B$13)+COUNTIFS(tblModel[status],"UNMATCHED_A",tblModel[gl_account],A30,tblModel[gl_account],$B$10,tblModel[source_account],$B$11,tblModel[posting_date],">="&$B$12,tblModel[posting_date],"<="&$B$13) -> 2
A31: =INDEX(Lists!$A:$A,6) -> 2100 | B31: =COUNTIFS(tblModel[status],"MISMATCH",tblModel[gl_account],A31,tblModel[gl_account],$B$10,tblModel[source_account],$B$11,tblModel[posting_date],">="&$B$12,tblModel[posting_date],"<="&$B$13)+COUNTIFS(tblModel[status],"UNMATCHED_A",tblModel[gl_account],A31,tblModel[gl_account],$B$10,tblModel[source_account],$B$11,tblModel[posting_date],">="&$B$12,tblModel[posting_date],"<="&$B$13) -> 0
A32: =INDEX(Lists!$A:$A,7) -> 3000 | B32: =COUNTIFS(tblModel[status],"MISMATCH",tblModel[gl_account],A32,tblModel[gl_account],$B$10,tblModel[source_account],$B$11,tblModel[posting_date],">="&$B$12,tblModel[posting_date],"<="&$B$13)+COUNTIFS(tblModel[status],"UNMATCHED_A",tblModel[gl_account],A32,tblModel[gl_account],$B$10,tblModel[source_account],$B$11,tblModel[posting_date],">="&$B$12,tblModel[posting_date],"<="&$B$13) -> 11
A33: =INDEX(Lists!$A:$A,8) -> 4000 | B33: =COUNTIFS(tblModel[status],"MISMATCH",tblModel[gl_account],A33,tblModel[gl_account],$B$10,tblModel[source_account],$B$11,tblModel[posting_date],">="&$B$12,tblModel[posting_date],"<="&$B$13)+COUNTIFS(tblModel[status],"UNMATCHED_A",tblModel[gl_account],A33,tblModel[gl_account],$B$10,tblModel[source_account],$B$11,tblModel[posting_date],">="&$B$12,tblModel[posting_date],"<="&$B$13) -> 5
A34: =INDEX(Lists!$A:$A,9) -> 5000 | B34: =COUNTIFS(tblModel[status],"MISMATCH",tblModel[gl_account],A34,tblModel[gl_account],$B$10,tblModel[source_account],$B$11,tblModel[posting_date],">="&$B$12,tblModel[posting_date],"<="&$B$13)+COUNTIFS(tblModel[status],"UNMATCHED_A",tblModel[gl_account],A34,tblModel[gl_account],$B$10,tblModel[source_account],$B$11,tblModel[posting_date],">="&$B$12,tblModel[posting_date],"<="&$B$13) -> 5
A35: =INDEX(Lists!$A:$A,10) -> 6000 | B35: =COUNTIFS(tblModel[status],"MISMATCH",tblModel[gl_account],A35,tblModel[gl_account],$B$10,tblModel[source_account],$B$11,tblModel[posting_date],">="&$B$12,tblModel[posting_date],"<="&$B$13)+COUNTIFS(tblModel[status],"UNMATCHED_A",tblModel[gl_account],A35,tblModel[gl_account],$B$10,tblModel[source_account],$B$11,tblModel[posting_date],">="&$B$12,tblModel[posting_date],"<="&$B$13) -> 2
A36: =INDEX(Lists!$A:$A,11) -> 7000 | B36: =COUNTIFS(tblModel[status],"MISMATCH",tblModel[gl_account],A36,tblModel[gl_account],$B$10,tblModel[source_account],$B$11,tblModel[posting_date],">="&$B$12,tblModel[posting_date],"<="&$B$13)+COUNTIFS(tblModel[status],"UNMATCHED_A",tblModel[gl_account],A36,tblModel[gl_account],$B$10,tblModel[source_account],$B$11,tblModel[posting_date],">="&$B$12,tblModel[posting_date],"<="&$B$13) -> 0

Sheet Overview
A1: Metric | B1: Value
A2: Total Rows | B2: 380
A3: EXACT_MATCH | B3: 212
A4: NEAR_MATCH | B4: 49
A5: MAPPING_ISSUE | B5: 0
A6: MISMATCH | B6: 39
A7: UNMATCHED_A | B7: 40
A8: UNMATCHED_B | B8: 40
A9: Amount Tolerance | B9: 1
A10: Date Tolerance (days) | B10: 2

Sheet StatusCounts
A1: status | B1: count
A2: EXACT_MATCH | B2: 212
A3: NEAR_MATCH | B3: 49
A4: MAPPING_ISSUE | B4: 0
A5: MISMATCH | B5: 39
A6: UNMATCHED_A | B6: 40
A7: UNMATCHED_B | B7: 40

Sheet Matches
A1: doc_id | B1: ref_id | C1: gl_account | D1: gl_account_name | E1: posting_date | F1: amount_A | G1: currency_A | H1: entity_A | I1: cost_center_A | J1: counterparty_A | K1: memo | L1: source_account | M1: source_account_name | N1: txn_date | O1: amount_B | P1: currency_B | Q1: entity_B | R1: cost_center_B | S1: counterparty_B | T1: description | U1: mapped_gl_account | V1: mapping_ok | W1: amount_diff | X1: days_diff | Y1: status
A2: TXN000001 | B2: TXN000001 | C2: 2000 | D2: Accounts Payable | E2: 45917 | F2: -922.63 | G2: USD | H2: US | I2: CC100 | K2: Subscription | L2: AP-VENDOR | M2: Subledger AP | N2: 45919 | O2: -913.31 | P2: USD | Q2: US | R2: CC100 | T2: Subscription | U2: 2000 | V2: TRUE | W2: -9.32 | X2: -2 | Y2: MISMATCH
A3: TXN000002 | B3: TXN000002 | C3: 1000 | D3: Cash | E3: 45880 | F3: 383.52 | G3: USD | H3: UK | I3: CC100 | J3: CustA | K3: Card fees | L3: BANK-SAV | M3: Bank Savings | N3: 45880 | O3: 383.52 | P3: USD | Q3: UK | R3: CC100 | S3: CustA | T3: Card fees | U3: 1000 | V3: TRUE | W3: 0 | X3: 0 | Y3: EXACT_MATCH
A4: TXN000003 | B4: TXN000003 | C4: 4000 | D4: COGS | E4: 45861 | F4: -508.21 | G4: USD | H4: IN | I4: CC100 | K4: Subscription | L4: COGS-INV | M4: COGS Inventory | N4: 45861 | O4: -508.21 | P4: USD | Q4: IN | R4: CC100 | T4: Subscription | U4: 4000 | V4: TRUE | W4: 0 | X4: 0 | Y4: EXACT_MATCH
A5: TXN000004 | B5: TXN000004 | C5: 1000 | D5: Cash | E5: 45917 | F5: -601.88 | G5: USD | H5: US | I5: CC400 | J5: CustA | K5: Adjustment | L5: BANK-SAV | M5: Bank Savings | N5: 45915 | O5: -594.58 | P5: USD | Q5: US | R5: CC400 | S5: CustA | T5: Adjustment | U5: 1000 | V5: TRUE | W5: -7.3 | X5: 2 | Y5: MISMATCH
A6: TXN000005 | B6: TXN000005 | C6: 1000 | D6: Cash | E6: 45892 | F6: 302.77 | G6: USD | H6: DE | I6: CC400 | J6: CustB | K6: Subscription | L6: BANK-CHK | M6: Bank Checking | N6: 45892 | O6: 302.77 | P6: USD | Q6: DE | R6: CC400 | S6: CustB | T6: Subscription | U6: 1000 | V6: TRUE | W6: 0 | X6: 0 | Y6: EXACT_MATCH
A7: TXN000006 | B7: TXN000006 | C7: 1000 | D7: Cash | E7: 45893 | F7: -500.52 | G7: USD | H7: UK | I7: CC100 | J7: VendY | K7: Subscription | L7: BANK-SAV | M7: Bank Savings | N7: 45893 | O7: -500.52 | P7: USD | Q7: UK | R7: CC100 | S7: VendY | T7: Subscription | U7: 1000 | V7: TRUE | W7: 0 | X7: 0 | Y7: EXACT_MATCH
A8: TXN000007 | B8: TXN000007 | C8: 3000 | D8: Revenue | E8: 45880 | F8: -499.78 | G8: USD | H8: US | I8: CC100 | J8: VendY | K8: Adjustment | L8: REV-ONLINE | M8: Revenue Online | N8: 45880 | O8: -499.78 | P8: USD | Q8: US | R8: CC100 | S8: VendY | T8: Adjustment | U8: 3000 | V8: TRUE | W8: 0 | X8: 0 | Y8: EXACT_MATCH
A9: TXN000008 | B9: TXN000008 | C9: 5000 | D9: Operating Expense | E9: 45900 | F9: 61.32 | G9: USD | H9: DE | I9: CC400 | J9: VendY | K9: Card fees | L9: OPEX-MKT | M9: Operating Marketing | N9: 45900 | O9: 61.32 | P9: USD | Q9: DE | R9: CC400 | S9: VendY | T9: Card fees | U9: 5000 | V9: TRUE | W9: 0 | X9: 0 | Y9: EXACT_MATCH
A10: TXN000009 | B10: TXN000009 | C10: 2000 | D10: Accounts Payable | E10: 45876 | F10: -754.41 | G10: USD | H10: UK | I10: CC200 | J10: CustA | K10: Subscription | L10: AP-VENDOR | M10: Subledger AP | N10: 45876 | O10: -754.41 | P10: USD | Q10: UK | R10: CC200 | S10: CustA | T10: Subscription | U10: 2000 | V10: TRUE | W10: 0 | X10: 0 | Y10: EXACT_MATCH
A11: TXN000010 | B11: TXN000010 | C11: 3000 | D11: Revenue | E11: 45890 | F11: 650.12 | G11: USD | H11: DE | I11: CC400 | J11: CustC | K11: Subscription | L11: REV-RETAIL | M11: Revenue Retail | N11: 45891 | O11: 649.17 | P11: USD | Q11: DE | R11: CC400 | S11: CustC | T11: Subscription | U11: 3000 | V11: TRUE | W11: 0.95 | X11: -1 | Y11: NEAR_MATCH
A12: TXN000011 | B12: TXN000011 | C12: 1000 | D12: Cash | E12: 45864 | F12: 343.64 | G12: USD | H12: UK | I12: CC300 | J12: CustB | K12: Card fees | L12: BANK-SAV | M12: Bank Savings | N12: 45865 | O12: 343.79 | P12: USD | Q12: UK | R12: CC300 | S12: CustB | T12: Card fees | U12: 1000 | V12: TRUE | W12: -0.15 | X12: -1 | Y12: NEAR_MATCH
A13: TXN000012 | B13: TXN000012 | C13: 4000 | D13: COGS | E13: 45859 | F13: 457.11 | G13: USD | H13: US | I13: CC300 | J13: CustC | K13: Refund | L13: COGS-INV | M13: COGS Inventory | N13: 45859 | O13: 457.11 | P13: USD | Q13: US | R13: CC300 | S13: CustC | T13: Refund | U13: 4000 | V13: TRUE | W13: 0 | X13: 0 | Y13: EXACT_MATCH
A14: TXN000013 | B14: TXN000013 | C14: 2000 | D14: Accounts Payable | E14: 45895 | F14: 626.32 | G14: USD | H14: IN | I14: CC100 | K14: Monthly activity | L14: AP-VENDOR | M14: Subledger AP | N14: 45895 | O14: 626.32 | P14: USD | Q14: IN | R14: CC100 | T14: Monthly activity | U14: 2000 | V14: TRUE | W14: 0 | X14: 0 | Y14: EXACT_MATCH
A15: TXN000014 | B15: TXN000014 | C15: 3000 | D15: Revenue | E15: 45887 | F15: 434.66 | G15: USD | H15: US | I15: CC100 | J15: VendZ | K15: Refund | L15: REV-RETAIL | M15: Revenue Retail | N15: 45890 | O15: 446.39 | P15: USD | Q15: US | R15: CC100 | S15: VendZ | T15: Refund | U15: 3000 | V15: TRUE | W15: -11.73 | X15: -3 | Y15: MISMATCH
A16: TXN000015 | B16: TXN000015 | C16: 3000 | D16: Revenue | E16: 45898 | F16: 439.31 | G16: USD | H16: IN | I16: CC300 | J16: VendZ | K16: Card fees | L16: REV-RETAIL | M16: Revenue Retail | N16: 45898 | O16: 439.31 | P16: USD | Q16: IN | R16: CC300 | S16: VendZ | T16: Card fees | U16: 3000 | V16: TRUE | W16: 0 | X16: 0 | Y16: EXACT_MATCH
A17: TXN000016 | B17: TXN000016 | C17: 2000 | D17: Accounts Payable | E17: 45858 | F17: 136.69 | G17: USD | H17: DE | I17: CC200 | J17: VendY | K17: Monthly activity | L17: AP-VENDOR | M17: Subledger AP | N17: 45858 | O17: 136.69 | P17: USD | Q17: DE | R17: CC200 | S17: VendY | T17: Monthly activity | U17: 2000 | V17: TRUE | W17: 0 | X17: 0 | Y17: EXACT_MATCH
A18: TXN000017 | B18: TXN000017 | C18: 5000 | D18: Operating Expense | E18: 45860 | F18: -638.65 | G18: USD | H18: DE | I18: CC200 | J18: VendZ | K18: Adjustment | L18: OPEX-MKT | M18: Operating Marketing | N18: 45859 | O18: -631.24 | P18: USD | Q18: DE | R18: CC200 | S18: VendZ | T18: Adjustment | U18: 5000 | V18: TRUE | W18: -7.41 | X18: 1 | Y18: MISMATCH
A19: TXN000018 | B19: TXN000018 | C19: 4000 | D19: COGS | E19: 45882 | F19: 530.97 | G19: USD | H19: IN | I19: CC100 | J19: CustB | K19: Card fees | L19: COGS-INV | M19: COGS Inventory | N19: 45882 | O19: 530.97 | P19: USD | Q19: IN | R19: CC100 | S19: CustB | T19: Card fees | U19: 4000 | V19: TRUE | W19: 0 | X19: 0 | Y19: EXACT_MATCH
A20: TXN000019 | B20: TXN000019 | C20: 4000 | D20: COGS | E20: 45892 | F20: -568.61 | G20: USD | H20: UK | I20: CC400 | K20: Subscription | L20: COGS-INV | M20: COGS Inventory | N20: 45892 | O20: -568.61 | P20: USD | Q20: UK | R20: CC400 | T20: Subscription | U20: 4000 | V20: TRUE | W20: 0 | X20: 0 | Y20: EXACT_MATCH
A21: TXN000020 | B21: TXN000020 | C21: 3000 | D21: Revenue | E21: 45902 | F21: 118.37 | G21: USD | H21: DE | I21: CC400 | J21: CustB | K21: Adjustment | L21: REV-RETAIL | M21: Revenue Retail | N21: 45902 | O21: 118.37 | P21: USD | Q21: DE | R21: CC400 | S21: CustB | T21: Adjustment | U21: 3000 | V21: TRUE | W21: 0 | X21: 0 | Y21: EXACT_MATCH
A22: TXN000021 | B22: TXN000021 | C22: 1000 | D22: Cash | E22: 45868 | F22: -912.67 | G22: USD | H22: UK | I22: CC100 | J22: VendX | L22: BANK-SAV | M22: Bank Savings | N22: 45870 | O22: -912.71 | P22: USD | Q22: UK | R22: CC100 | S22: VendX | U22: 1000 | V22: TRUE | W22: 0.04 | X22: -2 | Y22: NEAR_MATCH
A23: TXN000022 | B23: TXN000022 | C23: 6000 | D23: Other Income | E23: 45868 | F23: -538.58 | G23: USD | H23: US | I23: CC200 | J23: VendX | K23: Subscription | L23: MISC-INC | M23: Misc Income | N23: 45868 | O23: -538.58 | P23: USD | Q23: US | R23: CC200 | S23: VendX | T23: Subscription | U23: 6000 | V23: TRUE | W23: 0 | X23: 0 | Y23: EXACT_MATCH
A24: TXN000023 | B24: TXN000023 | C24: 2000 | D24: Accounts Payable | E24: 45896 | F24: 403.22 | G24: USD | H24: UK | I24: CC100 | J24: VendX | L24: AP-VENDOR | M24: Subledger AP | N24: 45896 | O24: 403.22 | P24: USD | Q24: UK | R24: CC100 | S24: VendX | U24: 2000 | V24: TRUE | W24: 0 | X24: 0 | Y24: EXACT_MATCH
A25: TXN000024 | B25: TXN000024 | C25: 5000 | D25: Operating Expense | E25: 45882 | F25: -1007.27 | G25: USD | H25: IN | I25: CC100 | J25: VendX | K25: Refund | L25: OPEX-IT | M25: Operating IT | N25: 45882 | O25: -1006.43 | P25: USD | Q25: IN | R25: CC100 | S25: VendX | T25: Refund | U25: 5000 | V25: TRUE | W25: -0.84 | X25: 0 | Y25: NEAR_MATCH
A26: TXN000025 | B26: TXN000025 | C26: 4000 | D26: COGS | E26: 45860 | F26: -488.65 | G26: USD | H26: UK | I26: CC400 | J26: CustB | K26: Monthly activity | L26: COGS-INV | M26: COGS Inventory | N26: 45861 | O26: -489.4 | P26: USD | Q26: UK | R26: CC400 | S26: CustB | T26: Monthly activity | U26: 4000 | V26: TRUE | W26: 0.75 | X26: -1 | Y26: NEAR_MATCH
A27: TXN000026 | B27: TXN000026 | C27: 2000 | D27: Accounts Payable | E27: 45895 | F27: -137.33 | G27: USD | H27: US | I27: CC200 | J27: VendY | K27: Monthly activity | L27: AP-VENDOR | M27: Subledger AP | N27: 45895 | O27: -137.33 | P27: USD | Q27: US | R27: CC200 | S27: VendY | T27: Monthly activity | U27: 2000 | V27: TRUE | W27: 0 | X27: 0 | Y27: EXACT_MATCH
A28: TXN000027 | B28: TXN000027 | C28: 2000 | D28: Accounts Payable | E28: 45896 | F28: -398.69 | G28: USD | H28: UK | I28: CC400 | J28: CustB | K28: Refund | L28: AP-VENDOR | M28: Subledger AP | N28: 45896 | O28: -398.69 | P28: USD | Q28: UK | R28: CC400 | S28: CustB | T28: Refund | U28: 2000 | V28: TRUE | W28: 0 | X28: 0 | Y28: EXACT_MATCH
A29: TXN000028 | B29: TXN000028 | C29: 3000 | D29: Revenue | E29: 45879 | F29: -72.08 | G29: USD | H29: IN | I29: CC100 | J29: CustA | L29: REV-RETAIL | M29: Revenue Retail | N29: 45879 | O29: -72.08 | P29: USD | Q29: IN | R29: CC100 | S29: CustA | U29: 3000 | V29: TRUE | W29: 0 | X29: 0 | Y29: EXACT_MATCH
A30: TXN000029 | B30: TXN000029 | C30: 5000 | D30: Operating Expense | E30: 45886 | F30: 762.35 | G30: USD | H30: DE | I30: CC100 | J30: CustB | K30: Monthly activity | L30: OPEX-MKT | M30: Operating Marketing | N30: 45886 | O30: 762.35 | P30: USD | Q30: DE | R30: CC100 | S30: CustB | T30: Monthly activity | U30: 5000 | V30: TRUE | W30: 0 | X30: 0 | Y30: EXACT_MATCH
A31: TXN000030 | B31: TXN000030 | C31: 2000 | D31: Accounts Payable | E31: 45904 | F31: -395.88 | G31: USD | H31: UK | I31: CC100 | J31: CustB | K31: Subscription | L31: AP-VENDOR | M31: Subledger AP | N31: 45902 | O31: -393.87 | P31: USD | Q31: UK | R31: CC100 | S31: CustB | T31: Subscription | U31: 2000 | V31: TRUE | W31: -2.01 | X31: 2 | Y31: MISMATCH
A32: TXN000031 | B32: TXN000031 | C32: 2000 | D32: Accounts Payable | E32: 45866 | F32: 314.36 | G32: USD | H32: US | I32: CC300 | J32: VendZ | L32: AP-VENDOR | M32: Subledger AP | N32: 45866 | O32: 314.36 | P32: USD | Q32: US | R32: CC300 | S32: VendZ | U32: 2000 | V32: TRUE | W32: 0 | X32: 0 | Y32: EXACT_MATCH
A33: TXN000032 | B33: TXN000032 | C33: 1000 | D33: Cash | E33: 45901 | F33: 768.12 | G33: USD | H33: DE | I33: CC200 | J33: CustC | L33: BANK-SAV | M33: Bank Savings | N33: 45901 | O33: 768.12 | P33: USD | Q33: DE | R33: CC200 | S33: CustC | U33: 1000 | V33: TRUE | W33: 0 | X33: 0 | Y33: EXACT_MATCH
A34: TXN000033 | B34: TXN000033 | C34: 3000 | D34: Revenue | E34: 45891 | F34: 87.23 | G34: USD | H34: DE | I34: CC200 | J34: VendY | L34: REV-ONLINE | M34: Revenue Online | N34: 45891 | O34: 86.84 | P34: USD | Q34: DE | R34: CC200 | S34: VendY | U34: 3000 | V34: TRUE | W34: 0.39 | X34: 0 | Y34: NEAR_MATCH
A35: TXN000034 | B35: TXN000034 | C35: 3000 | D35: Revenue | E35: 45908 | F35: -633.86 | G35: USD | H35: IN | I35: CC200 | J35: CustB | K35: Subscription | L35: REV-ONLINE | M35: Revenue Online | N35: 45908 | O35: -633.86 | P35: USD | Q35: IN | R35: CC200 | S35: CustB | T35: Subscription | U35: 3000 | V35: TRUE | W35: 0 | X35: 0 | Y35: EXACT_MATCH
A36: TXN000035 | B36: TXN000035 | C36: 5000 | D36: Operating Expense | E36: 45879 | F36: -16.1 | G36: USD | H36: US | I36: CC300 | J36: VendX | K36: Invoice settlement | L36: OPEX-MKT | M36: Operating Marketing | N36: 45881 | O36: -16.82 | P36: USD | Q36: US | R36: CC300 | S36: VendX | T36: Invoice settlement | U36: 5000 | V36: TRUE | W36: 0.72 | X36: -2 | Y36: NEAR_MATCH
A37: TXN000036 | B37: TXN000036 | C37: 3000 | D37: Revenue | E37: 45901 | F37: 334.46 | G37: USD | H37: DE | I37: CC400 | K37: Refund | L37: REV-ONLINE | M37: Revenue Online | N37: 45901 | O37: 334.46 | P37: USD | Q37: DE | R37: CC400 | T37: Refund | U37: 3000 | V37: TRUE | W37: 0 | X37: 0 | Y37: EXACT_MATCH
A38: TXN000037 | B38: TXN000037 | C38: 2000 | D38: Accounts Payable | E38: 45880 | F38: -198.95 | G38: USD | H38: US | I38: CC200 | J38: VendX | K38: Adjustment | L38: AP-VENDOR | M38: Subledger AP | N38: 45880 | O38: -198.95 | P38: USD | Q38: US | R38: CC200 | S38: VendX | T38: Adjustment | U38: 2000 | V38: TRUE | W38: 0 | X38: 0 | Y38: EXACT_MATCH
A39: TXN000038 | B39: TXN000038 | C39: 2000 | D39: Accounts Payable | E39: 45870 | F39: 865.49 | G39: USD | H39: US | I39: CC400 | J39: VendZ | K39: Invoice settlement | L39: AP-VENDOR | M39: Subledger AP | N39: 45870 | O39: 865.49 | P39: USD | Q39: US | R39: CC400 | S39: VendZ | T39: Invoice settlement | U39: 2000 | V39: TRUE | W39: 0 | X39: 0 | Y39: EXACT_MATCH
A40: TXN000039 | B40: TXN000039 | C40: 1000 | D40: Cash | E40: 45910 | F40: 941.54 | G40: USD | H40: IN | I40: CC200 | J40: VendX | K40: Adjustment | L40: BANK-SAV | M40: Bank Savings | N40: 45910 | O40: 942.35 | P40: USD | Q40: IN | R40: CC200 | S40: VendX | T40: Adjustment | U40: 1000 | V40: TRUE | W40: -0.81 | X40: 0 | Y40: NEAR_MATCH
A41: TXN000040 | B41: TXN000040 | C41: 4000 | D41: COGS | E41: 45907 | F41: 417.65 | G41: USD | H41: US | I41: CC400 | J41: VendX | K41: Card fees | L41: COGS-INV | M41: COGS Inventory | N41: 45907 | O41: 417.84 | P41: USD | Q41: US | R41: CC400 | S41: VendX | T41: Card fees | U41: 4000 | V41: TRUE | W41: -0.19 | X41: 0 | Y41: NEAR_MATCH
A42: TXN000041 | B42: TXN000041 | C42: 1000 | D42: Cash | E42: 45903 | F42: -710.18 | G42: USD | H42: UK | I42: CC100 | J42: CustB | K42: Subscription | L42: BANK-SAV | M42: Bank Savings | N42: 45903 | O42: -710.18 | P42: USD | Q42: UK | R42: CC100 | S42: CustB | T42: Subscription | U42: 1000 | V42: TRUE | W42: 0 | X42: 0 | Y42: EXACT_MATCH
A43: TXN000042 | B43: TXN000042 | C43: 5000 | D43: Operating Expense | E43: 45908 | F43: 455 | G43: USD | H43: IN | I43: CC300 | J43: CustB | K43: Subscription | L43: OPEX-MKT | M43: Operating Marketing | N43: 45908 | O43: 455 | P43: USD | Q43: IN | R43: CC300 | S43: CustB | T43: Subscription | U43: 5000 | V43: TRUE | W43: 0 | X43: 0 | Y43: EXACT_MATCH
A44: TXN000043 | B44: TXN000043 | C44: 5000 | D44: Operating Expense | E44: 45865 | F44: -642.02 | G44: USD | H44: US | I44: CC200 | J44: VendX | L44: OPEX-IT | M44: Operating IT | N44: 45865 | O44: -642.02 | P44: USD | Q44: US | R44: CC200 | S44: VendX | U44: 5000 | V44: TRUE | W44: 0 | X44: 0 | Y44: EXACT_MATCH
A45: TXN000044 | B45: TXN000044 | C45: 3000 | D45: Revenue | E45: 45909 | F45: 311.79 | G45: USD | H45: US | I45: CC300 | J45: CustB | K45: Invoice settlement | L45: REV-ONLINE | M45: Revenue Online | N45: 45910 | O45: 311.27 | P45: USD | Q45: US | R45: CC300 | S45: CustB | T45: Invoice settlement | U45: 3000 | V45: TRUE | W45: 0.52 | X45: -1 | Y45: NEAR_MATCH
A46: TXN000045 | B46: TXN000045 | C46: 5000 | D46: Operating Expense | E46: 45872 | F46: 72.92 | G46: USD | H46: DE | I46: CC300 | J46: VendY | K46: Card fees | L46: OPEX-IT | M46: Operating IT | N46: 45872 | O46: 72.92 | P46: USD | Q46: DE | R46: CC300 | S46: VendY | T46: Card fees | U46: 5000 | V46: TRUE | W46: 0 | X46: 0 | Y46: EXACT_MATCH
A47: TXN000046 | B47: TXN000046 | C47: 1100 | D47: Accounts Receivable | E47: 45860 | F47: 49.23 | G47: USD | H47: DE | I47: CC400 | J47: VendZ | K47: Subscription | L47: AR-CUST | M47: Subledger AR | N47: 45860 | O47: 49.23 | P47: USD | Q47: DE | R47: CC400 | S47: VendZ | T47: Subscription | U47: 1100 | V47: TRUE | W47: 0 | X47: 0 | Y47: EXACT_MATCH
A48: TXN000047 | B48: TXN000047 | C48: 5000 | D48: Operating Expense | E48: 45883 | F48: 595.78 | G48: USD | H48: UK | I48: CC200 | J48: VendY | K48: Subscription | L48: OPEX-IT | M48: Operating IT | N48: 45883 | O48: 595.78 | P48: USD | Q48: UK | R48: CC200 | S48: VendY | T48: Subscription | U48: 5000 | V48: TRUE | W48: 0 | X48: 0 | Y48: EXACT_MATCH
A49: TXN000048 | B49: TXN000048 | C49: 1000 | D49: Cash | E49: 45912 | F49: 1061.9 | G49: USD | H49: UK | I49: CC100 | L49: BANK-CHK | M49: Bank Checking | N49: 45912 | O49: 1061.9 | P49: USD | Q49: UK | R49: CC100 | U49: 1000 | V49: TRUE | W49: 0 | X49: 0 | Y49: EXACT_MATCH
A50: TXN000049 | B50: TXN000049 | C50: 1100 | D50: Accounts Receivable | E50: 45868 | F50: -567.35 | G50: USD | H50: US | I50: CC100 | J50: CustC | K50: Refund | L50: AR-CUST | M50: Subledger AR | N50: 45868 | O50: -567.35 | P50: USD | Q50: US | R50: CC100 | S50: CustC | T50: Refund | U50: 1100 | V50: TRUE | W50: 0 | X50: 0 | Y50: EXACT_MATCH
A51: TXN000050 | B51: TXN000050 | C51: 5000 | D51: Operating Expense | E51: 45890 | F51: 368.85 | G51: USD | H51: US | I51: CC100 | J51: CustB | K51: Adjustment | L51: OPEX-IT | M51: Operating IT | N51: 45890 | O51: 368.85 | P51: USD | Q51: US | R51: CC100 | S51: CustB | T51: Adjustment | U51: 5000 | V51: TRUE | W51: 0 | X51: 0 | Y51: EXACT_MATCH
A52: TXN000051 | B52: TXN000051 | C52: 3000 | D52: Revenue | E52: 45859 | F52: 978 | G52: USD | H52: IN | I52: CC100 | K52: Monthly activity | L52: REV-RETAIL | M52: Revenue Retail | N52: 45859 | O52: 978 | P52: USD | Q52: IN | R52: CC100 | T52: Monthly activity | U52: 3000 | V52: TRUE | W52: 0 | X52: 0 | Y52: EXACT_MATCH
A53: TXN000052 | B53: TXN000052 | C53: 5000 | D53: Operating Expense | E53: 45877 | F53: 559.33 | G53: USD | H53: UK | I53: CC300 | J53: VendX | K53: Subscription | L53: OPEX-MKT | M53: Operating Marketing | N53: 45877 | O53: 559.33 | P53: USD | Q53: UK | R53: CC300 | S53: VendX | T53: Subscription | U53: 5000 | V53: TRUE | W53: 0 | X53: 0 | Y53: EXACT_MATCH
A54: TXN000053 | B54: TXN000053 | C54: 5000 | D54: Operating Expense | E54: 45908 | F54: 525.36 | G54: USD | H54: UK | I54: CC300 | J54: VendY | K54: Adjustment | L54: OPEX-IT | M54: Operating IT | N54: 45908 | O54: 525.36 | P54: USD | Q54: UK | R54: CC300 | S54: VendY | T54: Adjustment | U54: 5000 | V54: TRUE | W54: 0 | X54: 0 | Y54: EXACT_MATCH
A55: TXN000054 | B55: TXN000054 | C55: 5000 | D55: Operating Expense | E55: 45865 | F55: 563.14 | G55: USD | H55: IN | I55: CC400 | J55: CustC | K55: Monthly activity | L55: OPEX-MKT | M55: Operating Marketing | N55: 45865 | O55: 563.14 | P55: USD | Q55: IN | R55: CC400 | S55: CustC | T55: Monthly activity | U55: 5000 | V55: TRUE | W55: 0 | X55: 0 | Y55: EXACT_MATCH
A56: TXN000055 | B56: TXN000055 | C56: 3000 | D56: Revenue | E56: 45884 | F56: -466.91 | G56: USD | H56: DE | I56: CC100 | K56: Adjustment | L56: REV-ONLINE | M56: Revenue Online | N56: 45885 | O56: -467.28 | P56: USD | Q56: DE | R56: CC100 | T56: Adjustment | U56: 3000 | V56: TRUE | W56: 0.37 | X56: -1 | Y56: NEAR_MATCH
A57: TXN000056 | B57: TXN000056 | C57: 2000 | D57: Accounts Payable | E57: 45866 | F57: -422.63 | G57: USD | H57: UK | I57: CC400 | J57: CustB | K57: Refund | L57: AP-VENDOR | M57: Subledger AP | N57: 45866 | O57: -422.63 | P57: USD | Q57: UK | R57: CC400 | S57: CustB | T57: Refund | U57: 2000 | V57: TRUE | W57: 0 | X57: 0 | Y57: EXACT_MATCH
A58: TXN000057 | B58: TXN000057 | C58: 1000 | D58: Cash | E58: 45882 | F58: 141.26 | G58: USD | H58: UK | I58: CC200 | J58: CustB | K58: Refund | L58: BANK-SAV | M58: Bank Savings | N58: 45882 | O58: 141.26 | P58: USD | Q58: UK | R58: CC200 | S58: CustB | T58: Refund | U58: 1000 | V58: TRUE | W58: 0 | X58: 0 | Y58: EXACT_MATCH
A59: TXN000058 | B59: TXN000058 | C59: 4000 | D59: COGS | E59: 45889 | F59: 625.41 | G59: USD | H59: IN | I59: CC200 | J59: CustC | K59: Invoice settlement | L59: COGS-INV | M59: COGS Inventory | N59: 45889 | O59: 625.41 | P59: USD | Q59: IN | R59: CC200 | S59: CustC | T59: Invoice settlement | U59: 4000 | V59: TRUE | W59: 0 | X59: 0 | Y59: EXACT_MATCH
A60: TXN000059 | B60: TXN000059 | C60: 1000 | D60: Cash | E60: 45903 | F60: -476.31 | G60: USD | H60: DE | I60: CC400 | J60: VendX | K60: Refund | L60: BANK-SAV | M60: Bank Savings | N60: 45903 | O60: -476.31 | P60: USD | Q60: DE | R60: CC400 | S60: VendX | T60: Refund | U60: 1000 | V60: TRUE | W60: 0 | X60: 0 | Y60: EXACT_MATCH
A61: TXN000060 | B61: TXN000060 | C61: 1000 | D61: Cash | E61: 45881 | F61: -798.27 | G61: USD | H61: DE | I61: CC100 | J61: CustA | L61: BANK-CHK | M61: Bank Checking | N61: 45881 | O61: -798.27 | P61: USD | Q61: DE | R61: CC100 | S61: CustA | U61: 1000 | V61: TRUE | W61: 0 | X61: 0 | Y61: EXACT_MATCH
A62: TXN000061 | B62: TXN000061 | C62: 3000 | D62: Revenue | E62: 45913 | F62: -407.8 | G62: USD | H62: DE | I62: CC300 | J62: CustA | L62: REV-ONLINE | M62: Revenue Online | N62: 45914 | O62: -406.08 | P62: USD | Q62: DE | R62: CC300 | S62: CustA | U62: 3000 | V62: TRUE | W62: -1.72 | X62: -1 | Y62: MISMATCH
A63: TXN000062 | B63: TXN000062 | C63: 1100 | D63: Accounts Receivable | E63: 45874 | F63: 23.41 | G63: USD | H63: IN | I63: CC300 | J63: VendX | K63: Adjustment | L63: AR-CUST | M63: Subledger AR | N63: 45874 | O63: 23.41 | P63: USD | Q63: IN | R63: CC300 | S63: VendX | T63: Adjustment | U63: 1100 | V63: TRUE | W63: 0 | X63: 0 | Y63: EXACT_MATCH
A64: TXN000063 | B64: TXN000063 | C64: 5000 | D64: Operating Expense | E64: 45915 | F64: 475.1 | G64: USD | H64: IN | I64: CC300 | J64: CustA | K64: Invoice settlement | L64: OPEX-IT | M64: Operating IT | N64: 45915 | O64: 475.1 | P64: USD | Q64: IN | R64: CC300 | S64: CustA | T64: Invoice settlement | U64: 5000 | V64: TRUE | W64: 0 | X64: 0 | Y64: EXACT_MATCH
A65: TXN000064 | B65: TXN000064 | C65: 1000 | D65: Cash | E65: 45908 | F65: 924.88 | G65: USD | H65: IN | I65: CC100 | J65: CustC | K65: Monthly activity | L65: BANK-CHK | M65: Bank Checking | N65: 45908 | O65: 924.51 | P65: USD | Q65: IN | R65: CC100 | S65: CustC | T65: Monthly activity | U65: 1000 | V65: TRUE | W65: 0.37 | X65: 0 | Y65: NEAR_MATCH
A66: TXN000065 | B66: TXN000065 | C66: 1000 | D66: Cash | E66: 45908 | F66: -404.14 | G66: USD | H66: UK | I66: CC100 | J66: CustC | L66: BANK-SAV | M66: Bank Savings | N66: 45908 | O66: -404.14 | P66: USD | Q66: UK | R66: CC100 | S66: CustC | U66: 1000 | V66: TRUE | W66: 0 | X66: 0 | Y66: EXACT_MATCH
A67: TXN000066 | B67: TXN000066 | C67: 1000 | D67: Cash | E67: 45886 | F67: -277.54 | G67: USD | H67: IN | I67: CC300 | J67: VendY | K67: Adjustment | L67: BANK-SAV | M67: Bank Savings | N67: 45888 | O67: -272.59 | P67: USD | Q67: IN | R67: CC300 | S67: VendY | T67: Adjustment | U67: 1000 | V67: TRUE | W67: -4.95 | X67: -2 | Y67: MISMATCH
A68: TXN000067 | B68: TXN000067 | C68: 1000 | D68: Cash | E68: 45890 | F68: 201.6 | G68: USD | H68: US | I68: CC200 | J68: CustC | K68: Monthly activity | L68: BANK-CHK | M68: Bank Checking | N68: 45890 | O68: 201.6 | P68: USD | Q68: US | R68: CC200 | S68: CustC | T68: Monthly activity | U68: 1000 | V68: TRUE | W68: 0 | X68: 0 | Y68: EXACT_MATCH
A69: TXN000068 | B69: TXN000068 | C69: 1100 | D69: Accounts Receivable | E69: 45869 | F69: 237.5 | G69: USD | H69: DE | I69: CC200 | J69: CustC | K69: Card fees | L69: AR-CUST | M69: Subledger AR | N69: 45869 | O69: 237.5 | P69: USD | Q69: DE | R69: CC200 | S69: CustC | T69: Card fees | U69: 1100 | V69: TRUE | W69: 0 | X69: 0 | Y69: EXACT_MATCH
A70: TXN000069 | B70: TXN000069 | C70: 5000 | D70: Operating Expense | E70: 45900 | F70: -424.95 | G70: USD | H70: DE | I70: CC100 | J70: CustC | K70: Monthly activity | L70: OPEX-IT | M70: Operating IT | N70: 45900 | O70: -424.95 | P70: USD | Q70: DE | R70: CC100 | S70: CustC | T70: Monthly activity | U70: 5000 | V70: TRUE | W70: 0 | X70: 0 | Y70: EXACT_MATCH
A71: TXN000070 | B71: TXN000070 | C71: 1000 | D71: Cash | E71: 45858 | F71: 205 | G71: USD | H71: UK | I71: CC400 | J71: CustB | K71: Card fees | L71: BANK-CHK | M71: Bank Checking | N71: 45858 | O71: 205.18 | P71: USD | Q71: UK | R71: CC400 | S71: CustB | T71: Card fees | U71: 1000 | V71: TRUE | W71: -0.18 | X71: 0 | Y71: NEAR_MATCH
A72: TXN000071 | B72: TXN000071 | C72: 1000 | D72: Cash | E72: 45899 | F72: 874.41 | G72: USD | H72: IN | I72: CC400 | J72: VendY | L72: BANK-SAV | M72: Bank Savings | N72: 45899 | O72: 874.41 | P72: USD | Q72: IN | R72: CC400 | S72: VendY | U72: 1000 | V72: TRUE | W72: 0 | X72: 0 | Y72: EXACT_MATCH
A73: TXN000072 | B73: TXN000072 | C73: 4000 | D73: COGS | E73: 45889 | F73: -429.34 | G73: USD | H73: UK | I73: CC200 | J73: CustC | K73: Adjustment | L73: COGS-INV | M73: COGS Inventory | N73: 45889 | O73: -429.34 | P73: USD | Q73: UK | R73: CC200 | S73: CustC | T73: Adjustment | U73: 4000 | V73: TRUE | W73: 0 | X73: 0 | Y73: EXACT_MATCH
A74: TXN000073 | B74: TXN000073 | C74: 1100 | D74: Accounts Receivable | E74: 45882 | F74: 527.16 | G74: USD | H74: US | I74: CC200 | J74: CustA | K74: Monthly activity | L74: AR-CUST | M74: Subledger AR | N74: 45882 | O74: 527.16 | P74: USD | Q74: US | R74: CC200 | S74: CustA | T74: Monthly activity | U74: 1100 | V74: TRUE | W74: 0 | X74: 0 | Y74: EXACT_MATCH
A75: TXN000074 | B75: TXN000074 | C75: 3000 | D75: Revenue | E75: 45884 | F75: -859.56 | G75: USD | H75: US | I75: CC400 | K75: Subscription | L75: REV-RETAIL | M75: Revenue Retail | N75: 45884 | O75: -859.56 | P75: USD | Q75: US | R75: CC400 | T75: Subscription | U75: 3000 | V75: TRUE | W75: 0 | X75: 0 | Y75: EXACT_MATCH
A76: TXN000075 | B76: TXN000075 | C76: 3000 | D76: Revenue | E76: 45895 | F76: -875.83 | G76: USD | H76: DE | I76: CC100 | J76: VendX | K76: Adjustment | L76: REV-RETAIL | M76: Revenue Retail | N76: 45895 | O76: -875.83 | P76: USD | Q76: DE | R76: CC100 | S76: VendX | T76: Adjustment | U76: 3000 | V76: TRUE | W76: 0 | X76: 0 | Y76: EXACT_MATCH
A77: TXN000076 | B77: TXN000076 | C77: 1100 | D77: Accounts Receivable | E77: 45874 | F77: 446.82 | G77: USD | H77: DE | I77: CC300 | J77: CustC | K77: Subscription | L77: AR-CUST | M77: Subledger AR | N77: 45874 | O77: 446.82 | P77: USD | Q77: DE | R77: CC300 | S77: CustC | T77: Subscription | U77: 1100 | V77: TRUE | W77: 0 | X77: 0 | Y77: EXACT_MATCH
A78: TXN000077 | B78: TXN000077 | C78: 2000 | D78: Accounts Payable | E78: 45872 | F78: -582.99 | G78: USD | H78: DE | I78: CC200 | J78: CustC | K78: Adjustment | L78: AP-VENDOR | M78: Subledger AP | N78: 45874 | O78: -582.61 | P78: USD | Q78: DE | R78: CC200 | S78: CustC | T78: Adjustment | U78: 2000 | V78: TRUE | W78: -0.38 | X78: -2 | Y78: NEAR_MATCH
A79: TXN000078 | B79: TXN000078 | C79: 1000 | D79: Cash | E79: 45878 | F79: -683.76 | G79: USD | H79: IN | I79: CC300 | J79: VendY | K79: Refund | L79: BANK-CHK | M79: Bank Checking | N79: 45878 | O79: -683.76 | P79: USD | Q79: IN | R79: CC300 | S79: VendY | T79: Refund | U79: 1000 | V79: TRUE | W79: 0 | X79: 0 | Y79: EXACT_MATCH
A80: TXN000079 | B80: TXN000079 | C80: 3000 | D80: Revenue | E80: 45872 | F80: 451.79 | G80: USD | H80: US | I80: CC100 | J80: CustC | L80: REV-ONLINE | M80: Revenue Online | N80: 45872 | O80: 451.79 | P80: USD | Q80: US | R80: CC100 | S80: CustC | U80: 3000 | V80: TRUE | W80: 0 | X80: 0 | Y80: EXACT_MATCH
A81: TXN000080 | B81: TXN000080 | C81: 1000 | D81: Cash | E81: 45866 | F81: -55.5 | G81: USD | H81: US | I81: CC400 | J81: CustA | K81: Invoice settlement | L81: BANK-SAV | M81: Bank Savings | N81: 45867 | O81: -46.61 | P81: USD | Q81: US | R81: CC400 | S81: CustA | T81: Invoice settlement | U81: 1000 | V81: TRUE | W81: -8.89 | X81: -1 | Y81: MISMATCH
A82: TXN000081 | B82: TXN000081 | C82: 3000 | D82: Revenue | E82: 45897 | F82: -663.68 | G82: USD | H82: UK | I82: CC400 | K82: Invoice settlement | L82: REV-RETAIL | M82: Revenue Retail | N82: 45897 | O82: -663.68 | P82: USD | Q82: UK | R82: CC400 | T82: Invoice settlement | U82: 3000 | V82: TRUE | W82: 0 | X82: 0 | Y82: EXACT_MATCH
A83: TXN000082 | B83: TXN000082 | C83: 5000 | D83: Operating Expense | E83: 45866 | F83: -723.59 | G83: USD | H83: UK | I83: CC100 | L83: OPEX-MKT | M83: Operating Marketing | N83: 45869 | O83: -719.22 | P83: USD | Q83: UK | R83: CC100 | U83: 5000 | V83: TRUE | W83: -4.37 | X83: -3 | Y83: MISMATCH
A84: TXN000083 | B84: TXN000083 | C84: 5000 | D84: Operating Expense | E84: 45897 | F84: 603.88 | G84: USD | H84: UK | I84: CC100 | K84: Refund | L84: OPEX-IT | M84: Operating IT | N84: 45897 | O84: 603.18 | P84: USD | Q84: UK | R84: CC100 | T84: Refund | U84: 5000 | V84: TRUE | W84: 0.7 | X84: 0 | Y84: NEAR_MATCH
A85: TXN000084 | B85: TXN000084 | C85: 6000 | D85: Other Income | E85: 45908 | F85: 269.11 | G85: USD | H85: UK | I85: CC100 | J85: CustA | K85: Monthly activity | L85: MISC-INC | M85: Misc Income | N85: 45908 | O85: 269.11 | P85: USD | Q85: UK | R85: CC100 | S85: CustA | T85: Monthly activity | U85: 6000 | V85: TRUE | W85: 0 | X85: 0 | Y85: EXACT_MATCH
A86: TXN000085 | B86: TXN000085 | C86: 1100 | D86: Accounts Receivable | E86: 45897 | F86: -450.99 | G86: USD | H86: US | I86: CC400 | K86: Card fees | L86: AR-CUST | M86: Subledger AR | N86: 45897 | O86: -450.99 | P86: USD | Q86: US | R86: CC400 | T86: Card fees | U86: 1100 | V86: TRUE | W86: 0 | X86: 0 | Y86: EXACT_MATCH
A87: TXN000086 | B87: TXN000086 | C87: 5000 | D87: Operating Expense | E87: 45860 | F87: 352.31 | G87: USD | H87: UK | I87: CC400 | J87: CustC | K87: Monthly activity | L87: OPEX-IT | M87: Operating IT | N87: 45860 | O87: 352.31 | P87: USD | Q87: UK | R87: CC400 | S87: CustC | T87: Monthly activity | U87: 5000 | V87: TRUE | W87: 0 | X87: 0 | Y87: EXACT_MATCH
A88: TXN000087 | B88: TXN000087 | C88: 5000 | D88: Operating Expense | E88: 45908 | F88: -425.07 | G88: USD | H88: US | I88: CC100 | J88: VendZ | K88: Refund | L88: OPEX-MKT | M88: Operating Marketing | N88: 45908 | O88: -425.07 | P88: USD | Q88: US | R88: CC100 | S88: VendZ | T88: Refund | U88: 5000 | V88: TRUE | W88: 0 | X88: 0 | Y88: EXACT_MATCH
A89: TXN000088 | B89: TXN000088 | C89: 5000 | D89: Operating Expense | E89: 45873 | F89: 824.22 | G89: USD | H89: DE | I89: CC200 | J89: VendZ | L89: OPEX-MKT | M89: Operating Marketing | N89: 45873 | O89: 824.22 | P89: USD | Q89: DE | R89: CC200 | S89: VendZ | U89: 5000 | V89: TRUE | W89: 0 | X89: 0 | Y89: EXACT_MATCH
A90: TXN000089 | B90: TXN000089 | C90: 3000 | D90: Revenue | E90: 45871 | F90: 882.39 | G90: USD | H90: IN | I90: CC400 | K90: Card fees | L90: REV-ONLINE | M90: Revenue Online | N90: 45871 | O90: 882.39 | P90: USD | Q90: IN | R90: CC400 | T90: Card fees | U90: 3000 | V90: TRUE | W90: 0 | X90: 0 | Y90: EXACT_MATCH
A91: TXN000090 | B91: TXN000090 | C91: 1000 | D91: Cash | E91: 45887 | F91: 667.35 | G91: USD | H91: DE | I91: CC100 | J91: VendY | K91: Refund | L91: BANK-SAV | M91: Bank Savings | N91: 45887 | O91: 667.35 | P91: USD | Q91: DE | R91: CC100 | S91: VendY | T91: Refund | U91: 1000 | V91: TRUE | W91: 0 | X91: 0 | Y91: EXACT_MATCH
A92: TXN000091 | B92: TXN000091 | C92: 3000 | D92: Revenue | E92: 45861 | F92: 637.19 | G92: USD | H92: DE | I92: CC300 | J92: VendZ | K92: Refund | L92: REV-ONLINE | M92: Revenue Online | N92: 45863 | O92: 637.55 | P92: USD | Q92: DE | R92: CC300 | S92: VendZ | T92: Refund | U92: 3000 | V92: TRUE | W92: -0.36 | X92: -2 | Y92: NEAR_MATCH
A93: TXN000092 | B93: TXN000092 | C93: 3000 | D93: Revenue | E93: 45896 | F93: 669.16 | G93: USD | H93: US | I93: CC400 | J93: CustA | K93: Card fees | L93: REV-RETAIL | M93: Revenue Retail | N93: 45896 | O93: 669.16 | P93: USD | Q93: US | R93: CC400 | S93: CustA | T93: Card fees | U93: 3000 | V93: TRUE | W93: 0 | X93: 0 | Y93: EXACT_MATCH
A94: TXN000093 | B94: TXN000093 | C94: 3000 | D94: Revenue | E94: 45900 | F94: -496.94 | G94: USD | H94: UK | I94: CC400 | J94: CustC | K94: Refund | L94: REV-RETAIL | M94: Revenue Retail | N94: 45899 | O94: -496.97 | P94: USD | Q94: UK | R94: CC400 | S94: CustC | T94: Refund | U94: 3000 | V94: TRUE | W94: 0.03 | X94: 1 | Y94: NEAR_MATCH
A95: TXN000094 | B95: TXN000094 | C95: 5000 | D95: Operating Expense | E95: 45875 | F95: 481.08 | G95: USD | H95: IN | I95: CC100 | J95: VendY | K95: Adjustment | L95: OPEX-IT | M95: Operating IT | N95: 45877 | O95: 480.1 | P95: USD | Q95: IN | R95: CC100 | S95: VendY | T95: Adjustment | U95: 5000 | V95: TRUE | W95: 0.98 | X95: -2 | Y95: NEAR_MATCH
A96: TXN000095 | B96: TXN000095 | C96: 3000 | D96: Revenue | E96: 45862 | F96: 331.59 | G96: USD | H96: US | I96: CC300 | J96: VendX | K96: Monthly activity | L96: REV-RETAIL | M96: Revenue Retail | N96: 45860 | O96: 344.27 | P96: USD | Q96: US | R96: CC300 | S96: VendX | T96: Monthly activity | U96: 3000 | V96: TRUE | W96: -12.68 | X96: 2 | Y96: MISMATCH
A97: TXN000096 | B97: TXN000096 | C97: 5000 | D97: Operating Expense | E97: 45885 | F97: 486.03 | G97: USD | H97: IN | I97: CC200 | J97: CustB | K97: Monthly activity | L97: OPEX-IT | M97: Operating IT | N97: 45885 | O97: 486.03 | P97: USD | Q97: IN | R97: CC200 | S97: CustB | T97: Monthly activity | U97: 5000 | V97: TRUE | W97: 0 | X97: 0 | Y97: EXACT_MATCH
A98: TXN000097 | B98: TXN000097 | C98: 6000 | D98: Other Income | E98: 45862 | F98: -1064.99 | G98: USD | H98: DE | I98: CC300 | J98: CustB | K98: Subscription | L98: MISC-INC | M98: Misc Income | N98: 45862 | O98: -1064.99 | P98: USD | Q98: DE | R98: CC300 | S98: CustB | T98: Subscription | U98: 6000 | V98: TRUE | W98: 0 | X98: 0 | Y98: EXACT_MATCH
A99: TXN000098 | B99: TXN000098 | C99: 5000 | D99: Operating Expense | E99: 45874 | F99: 717.26 | G99: USD | H99: DE | I99: CC200 | J99: VendX | K99: Card fees | L99: OPEX-IT | M99: Operating IT | N99: 45874 | O99: 717.26 | P99: USD | Q99: DE | R99: CC200 | S99: VendX | T99: Card fees | U99: 5000 | V99: TRUE | W99: 0 | X99: 0 | Y99: EXACT_MATCH
A100: TXN000099 | B100: TXN000099 | C100: 4000 | D100: COGS | E100: 45858 | F100: -414.47 | G100: USD | H100: IN | I100: CC400 | J100: VendX | K100: Invoice settlement | L100: COGS-INV | M100: COGS Inventory | N100: 45861 | O100: -403.37 | P100: USD | Q100: IN | R100: CC400 | S100: VendX | T100: Invoice settlement | U100: 4000 | V100: TRUE | W100: -11.1 | X100: -3 | Y100: MISMATCH
...

Sheet Unmatched_A
A1: doc_id | B1: ref_id | C1: gl_account | D1: gl_account_name | E1: posting_date | F1: amount_A | G1: currency_A | H1: entity_A | I1: cost_center_A | J1: counterparty_A | K1: memo | L1: source_account | M1: source_account_name | N1: txn_date | O1: amount_B | P1: currency_B | Q1: entity_B | R1: cost_center_B | S1: counterparty_B | T1: description | U1: mapped_gl_account | V1: mapping_ok | W1: amount_diff | X1: days_diff | Y1: status
A2: AONLY00001 | C2: 2100 | D2: Accrued Expenses | E2: 45915 | F2: 600.89 | G2: USD | H2: DE | I2: CC300 | J2: CustB | K2: Manual JE | V2: FALSE | Y2: UNMATCHED_A
A3: AONLY00002 | C3: 2000 | D3: Accounts Payable | E3: 45892 | F3: 539.84 | G3: USD | H3: IN | I3: CC300 | J3: VendY | K3: Reclass | V3: FALSE | Y3: UNMATCHED_A
A4: AONLY00003 | C4: 6000 | D4: Other Income | E4: 45891 | F4: -278.74 | G4: USD | H4: IN | I4: CC100 | J4: CustC | K4: Accrual | V4: FALSE | Y4: UNMATCHED_A
A5: AONLY00004 | C5: 2100 | D5: Accrued Expenses | E5: 45860 | F5: 98.2 | G5: USD | H5: UK | I5: CC100 | J5: VendY | K5: Reclass | V5: FALSE | Y5: UNMATCHED_A
A6: AONLY00005 | C6: 6000 | D6: Other Income | E6: 45871 | F6: 509.6 | G6: USD | H6: UK | I6: CC400 | J6: CustC | K6: Manual JE | V6: FALSE | Y6: UNMATCHED_A
A7: AONLY00006 | C7: 2100 | D7: Accrued Expenses | E7: 45907 | F7: 885.62 | G7: USD | H7: UK | I7: CC400 | K7: Accrual | V7: FALSE | Y7: UNMATCHED_A
A8: AONLY00007 | C8: 4000 | D8: COGS | E8: 45911 | F8: 485 | G8: USD | H8: US | I8: CC400 | K8: Reclass | V8: FALSE | Y8: UNMATCHED_A
A9: AONLY00008 | C9: 3000 | D9: Revenue | E9: 45857 | F9: 142.07 | G9: USD | H9: IN | I9: CC400 | J9: VendX | K9: Reclass | V9: FALSE | Y9: UNMATCHED_A
A10: AONLY00009 | C10: 7000 | D10: Other Expense | E10: 45871 | F10: -534.73 | G10: USD | H10: DE | I10: CC300 | K10: Manual JE | V10: FALSE | Y10: UNMATCHED_A
A11: AONLY00010 | C11: 2100 | D11: Accrued Expenses | E11: 45893 | F11: 834.33 | G11: USD | H11: DE | I11: CC300 | J11: VendY | K11: Manual JE | V11: FALSE | Y11: UNMATCHED_A
A12: AONLY00011 | C12: 1000 | D12: Cash | E12: 45895 | F12: 670.81 | G12: USD | H12: IN | I12: CC100 | J12: VendZ | K12: Accrual | V12: FALSE | Y12: UNMATCHED_A
A13: AONLY00012 | C13: 2000 | D13: Accounts Payable | E13: 45883 | F13: 748.39 | G13: USD | H13: IN | I13: CC300 | J13: VendZ | K13: Manual JE | V13: FALSE | Y13: UNMATCHED_A
A14: AONLY00013 | C14: 6000 | D14: Other Income | E14: 45868 | F14: -292.49 | G14: USD | H14: DE | I14: CC300 | K14: Manual JE | V14: FALSE | Y14: UNMATCHED_A
A15: AONLY00014 | C15: 4000 | D15: COGS | E15: 45868 | F15: -467.15 | G15: USD | H15: US | I15: CC300 | J15: VendY | K15: Manual JE | V15: FALSE | Y15: UNMATCHED_A
A16: AONLY00015 | C16: 2100 | D16: Accrued Expenses | E16: 45882 | F16: 407.17 | G16: USD | H16: US | I16: CC100 | J16: CustB | K16: Accrual | V16: FALSE | Y16: UNMATCHED_A
A17: AONLY00016 | C17: 4000 | D17: COGS | E17: 45895 | F17: -622.07 | G17: USD | H17: UK | I17: CC100 | J17: CustA | K17: Accrual | V17: FALSE | Y17: UNMATCHED_A
A18: AONLY00017 | C18: 1000 | D18: Cash | E18: 45898 | F18: -333.82 | G18: USD | H18: DE | I18: CC200 | J18: VendZ | K18: Accrual | V18: FALSE | Y18: UNMATCHED_A
A19: AONLY00018 | C19: 3000 | D19: Revenue | E19: 45869 | F19: 573.7 | G19: USD | H19: IN | I19: CC100 | J19: CustA | K19: Accrual | V19: FALSE | Y19: UNMATCHED_A
A20: AONLY00019 | C20: 2000 | D20: Accounts Payable | E20: 45871 | F20: -221.21 | G20: USD | H20: UK | I20: CC300 | J20: CustA | K20: Reclass | V20: FALSE | Y20: UNMATCHED_A
A21: AONLY00020 | C21: 7000 | D21: Other Expense | E21: 45871 | F21: 132.9 | G21: USD | H21: IN | I21: CC400 | J21: CustA | K21: Accrual | V21: FALSE | Y21: UNMATCHED_A
A22: AONLY00021 | C22: 4000 | D22: COGS | E22: 45892 | F22: -329.41 | G22: USD | H22: DE | I22: CC400 | J22: CustC | K22: Reclass | V22: FALSE | Y22: UNMATCHED_A
A23: AONLY00022 | C23: 5000 | D23: Operating Expense | E23: 45875 | F23: -320.72 | G23: USD | H23: IN | I23: CC100 | J23: CustC | K23: Manual JE | V23: FALSE | Y23: UNMATCHED_A
A24: AONLY00023 | C24: 2100 | D24: Accrued Expenses | E24: 45891 | F24: 472.79 | G24: USD | H24: UK | I24: CC400 | J24: VendX | K24: Accrual | V24: FALSE | Y24: UNMATCHED_A
A25: AONLY00024 | C25: 2100 | D25: Accrued Expenses | E25: 45917 | F25: 619.95 | G25: USD | H25: UK | I25: CC200 | K25: Reclass | V25: FALSE | Y25: UNMATCHED_A
A26: AONLY00025 | C26: 6000 | D26: Other Income | E26: 45872 | F26: 642.49 | G26: USD | H26: UK | I26: CC200 | K26: Accrual | V26: FALSE | Y26: UNMATCHED_A
A27: AONLY00026 | C27: 2100 | D27: Accrued Expenses | E27: 45857 | F27: -578.41 | G27: USD | H27: US | I27: CC200 | K27: Accrual | V27: FALSE | Y27: UNMATCHED_A
A28: AONLY00027 | C28: 6000 | D28: Other Income | E28: 45905 | F28: -393.29 | G28: USD | H28: US | I28: CC300 | J28: CustA | K28: Accrual | V28: FALSE | Y28: UNMATCHED_A
A29: AONLY00028 | C29: 5000 | D29: Operating Expense | E29: 45906 | F29: 1045.49 | G29: USD | H29: UK | I29: CC300 | J29: CustB | K29: Accrual | V29: FALSE | Y29: UNMATCHED_A
A30: AONLY00029 | C30: 2000 | D30: Accounts Payable | E30: 45911 | F30: 633.61 | G30: USD | H30: US | I30: CC200 | J30: CustC | K30: Accrual | V30: FALSE | Y30: UNMATCHED_A
A31: AONLY00030 | C31: 7000 | D31: Other Expense | E31: 45867 | F31: 696.21 | G31: USD | H31: DE | I31: CC200 | J31: VendX | K31: Manual JE | V31: FALSE | Y31: UNMATCHED_A
A32: AONLY00031 | C32: 6000 | D32: Other Income | E32: 45873 | F32: 765.03 | G32: USD | H32: DE | I32: CC100 | J32: CustA | K32: Manual JE | V32: FALSE | Y32: UNMATCHED_A
A33: AONLY00032 | C33: 1000 | D33: Cash | E33: 45907 | F33: -349.73 | G33: USD | H33: DE | I33: CC100 | J33: VendX | K33: Manual JE | V33: FALSE | Y33: UNMATCHED_A
A34: AONLY00033 | C34: 3000 | D34: Revenue | E34: 45917 | F34: 473 | G34: USD | H34: IN | I34: CC300 | J34: VendZ | K34: Manual JE | V34: FALSE | Y34: UNMATCHED_A
A35: AONLY00034 | C35: 5000 | D35: Operating Expense | E35: 45905 | F35: -339.76 | G35: USD | H35: DE | I35: CC200 | J35: VendY | K35: Accrual | V35: FALSE | Y35: UNMATCHED_A
A36: AONLY00035 | C36: 4000 | D36: COGS | E36: 45862 | F36: -975.48 | G36: USD | H36: DE | I36: CC200 | J36: CustB | K36: Manual JE | V36: FALSE | Y36: UNMATCHED_A
A37: AONLY00036 | C37: 1200 | D37: Prepaid Expenses | E37: 45916 | F37: 422.39 | G37: USD | H37: DE | I37: CC200 | J37: VendZ | K37: Accrual | V37: FALSE | Y37: UNMATCHED_A
A38: AONLY00037 | C38: 1200 | D38: Prepaid Expenses | E38: 45895 | F38: 501.18 | G38: USD | H38: IN | I38: CC200 | J38: CustA | K38: Manual JE | V38: FALSE | Y38: UNMATCHED_A
A39: AONLY00038 | C39: 2100 | D39: Accrued Expenses | E39: 45869 | F39: -161.63 | G39: USD | H39: DE | I39: CC400 | J39: CustA | K39: Accrual | V39: FALSE | Y39: UNMATCHED_A
... A41: AONLY00040 | C41: 2000 | D41: Accounts Payable | E41: 45907 | F41: 524.17 | G41: USD | H41: US | I41: CC300 | J41: CustA | K41: Manual JE | V41: FALSE | Y41: UNMATCHED_A

Sheet Unmatched_B
A1: doc_id | B1: ref_id | C1: gl_account | D1: gl_account_name | E1: posting_date | F1: amount_A | G1: currency_A | H1: entity_A | I1: cost_center_A | J1: counterparty_A | K1: memo | L1: source_account | M1: source_account_name | N1: txn_date | O1: amount_B | P1: currency_B | Q1: entity_B | R1: cost_center_B | S1: counterparty_B | T1: description | U1: mapped_gl_account | V1: mapping_ok | W1: amount_diff | X1: days_diff | Y1: status
B2: BONLY00001 | L2: BANK-SAV | M2: Bank Savings | N2: 45904 | O2: 468.33 | P2: USD | Q2: IN | R2: CC200 | S2: VendZ | T2: Misc receipt | U2: 1000 | V2: FALSE | Y2: UNMATCHED_B
B3: BONLY00002 | L3: OPEX-MKT | M3: Operating Marketing | N3: 45909 | O3: -696.95 | P3: USD | Q3: UK | R3: CC300 | S3: CustB | T3: Chargeback | U3: 5000 | V3: FALSE | Y3: UNMATCHED_B
B4: BONLY00003 | L4: REV-ONLINE | M4: Revenue Online | N4: 45877 | O4: 428.21 | P4: USD | Q4: IN | R4: CC300 | S4: CustC | T4: Chargeback | U4: 3000 | V4: FALSE | Y4: UNMATCHED_B
B5: BONLY00004 | L5: OPEX-MKT | M5: Operating Marketing | N5: 45899 | O5: -743.22 | P5: USD | Q5: IN | R5: CC400 | S5: CustC | T5: Bank fee | U5: 5000 | V5: FALSE | Y5: UNMATCHED_B
B6: BONLY00005 | L6: AP-VENDOR | M6: Subledger AP | N6: 45865 | O6: 622.46 | P6: USD | Q6: DE | R6: CC100 | S6: VendZ | T6: Misc receipt | U6: 2000 | V6: FALSE | Y6: UNMATCHED_B
B7: BONLY00006 | L7: BANK-CHK | M7: Bank Checking | N7: 45883 | O7: 769.89 | P7: USD | Q7: US | R7: CC400 | S7: VendX | T7: Chargeback | U7: 1000 | V7: FALSE | Y7: UNMATCHED_B
B8: BONLY00007 | L8: OPEX-MKT | M8: Operating Marketing | N8: 45875 | O8: 696.92 | P8: USD | Q8: DE | R8: CC300 | S8: VendX | T8: Misc receipt | U8: 5000 | V8: FALSE | Y8: UNMATCHED_B
B9: BONLY00008 | L9: AR-CUST | M9: Subledger AR | N9: 45891 | O9: -608.48 | P9: USD | Q9: UK | R9: CC400 | S9: VendY | T9: Misc receipt | U9: 1100 | V9: FALSE | Y9: UNMATCHED_B
B10: BONLY00009 | L10: REV-ONLINE | M10: Revenue Online | N10: 45877 | O10: -95.43 | P10: USD | Q10: IN | R10: CC100 | S10: CustA | T10: Bank fee | U10: 3000 | V10: FALSE | Y10: UNMATCHED_B
B11: BONLY00010 | L11: COGS-INV | M11: COGS Inventory | N11: 45890 | O11: 323.98 | P11: USD | Q11: IN | R11: CC400 | S11: VendX | T11: Late fee | U11: 4000 | V11: FALSE | Y11: UNMATCHED_B
B12: BONLY00011 | L12: OPEX-IT | M12: Operating IT | N12: 45871 | O12: -395.02 | P12: USD | Q12: DE | R12: CC400 | S12: VendZ | T12: Chargeback | U12: 5000 | V12: FALSE | Y12: UNMATCHED_B
B13: BONLY00012 | L13: BANK-SAV | M13: Bank Savings | N13: 45867 | O13: -828.07 | P13: USD | Q13: DE | R13: CC100 | T13: Late fee | U13: 1000 | V13: FALSE | Y13: UNMATCHED_B
B14: BONLY00013 | L14: COGS-INV | M14: COGS Inventory | N14: 45897 | O14: -117.4 | P14: USD | Q14: DE | R14: CC200 | S14: VendY | T14: Chargeback | U14: 4000 | V14: FALSE | Y14: UNMATCHED_B
B15: BONLY00014 | L15: BANK-CHK | M15: Bank Checking | N15: 45901 | O15: 712.23 | P15: USD | Q15: US | R15: CC300 | S15: VendZ | T15: Bank fee | U15: 1000 | V15: FALSE | Y15: UNMATCHED_B
B16: BONLY00015 | L16: OPEX-MKT | M16: Operating Marketing | N16: 45906 | O16: 346.62 | P16: USD | Q16: DE | R16: CC200 | S16: VendY | T16: Chargeback | U16: 5000 | V16: FALSE | Y16: UNMATCHED_B
B17: BONLY00016 | L17: BANK-SAV | M17: Bank Savings | N17: 45867 | O17: -190.38 | P17: USD | Q17: IN | R17: CC400 | S17: VendY | T17: Misc receipt | U17: 1000 | V17: FALSE | Y17: UNMATCHED_B
B18: BONLY00017 | L18: AP-VENDOR | M18: Subledger AP | N18: 45874 | O18: -154.05 | P18: USD | Q18: DE | R18: CC100 | T18: Bank fee | U18: 2000 | V18: FALSE | Y18: UNMATCHED_B
B19: BONLY00018 | L19: COGS-INV | M19: COGS Inventory | N19: 45894 | O19: 315.94 | P19: USD | Q19: US | R19: CC400 | S19: CustA | T19: Chargeback | U19: 4000 | V19: FALSE | Y19: UNMATCHED_B
B20: BONLY00019 | L20: REV-RETAIL | M20: Revenue Retail | N20: 45883 | O20: 411.54 | P20: USD | Q20: IN | R20: CC100 | S20: CustB | T20: Misc receipt | U20: 3000 | V20: FALSE | Y20: UNMATCHED_B
B21: BONLY00020 | L21: BANK-SAV | M21: Bank Savings | N21: 45868 | O21: -496.72 | P21: USD | Q21: IN | R21: CC200 | S21: CustA | T21: Late fee | U21: 1000 | V21: FALSE | Y21: UNMATCHED_B
B22: BONLY00021 | L22: BANK-SAV | M22: Bank Savings | N22: 45864 | O22: 405.65 | P22: USD | Q22: DE | R22: CC200 | S22: VendX | T22: Chargeback | U22: 1000 | V22: FALSE | Y22: UNMATCHED_B
B23: BONLY00022 | L23: BANK-CHK | M23: Bank Checking | N23: 45878 | O23: 728.07 | P23: USD | Q23: UK | R23: CC200 | S23: CustA | T23: Chargeback | U23: 1000 | V23: FALSE | Y23: UNMATCHED_B
B24: BONLY00023 | L24: AR-CUST | M24: Subledger AR | N24: 45880 | O24: -631.13 | P24: USD | Q24: IN | R24: CC400 | S24: VendZ | T24: Chargeback | U24: 1100 | V24: FALSE | Y24: UNMATCHED_B
B25: BONLY00024 | L25: AR-CUST | M25: Subledger AR | N25: 45917 | O25: 298.46 | P25: USD | Q25: DE | R25: CC400 | S25: VendY | T25: Late fee | U25: 1100 | V25: FALSE | Y25: UNMATCHED_B
B26: BONLY00025 | L26: OPEX-IT | M26: Operating IT | N26: 45862 | O26: 587.28 | P26: USD | Q26: DE | R26: CC400 | S26: CustA | T26: Chargeback | U26: 5000 | V26: FALSE | Y26: UNMATCHED_B
B27: BONLY00026 | L27: AP-VENDOR | M27: Subledger AP | N27: 45869 | O27: 400.33 | P27: USD | Q27: US | R27: CC100 | S27: VendY | T27: Late fee | U27: 2000 | V27: FALSE | Y27: UNMATCHED_B
B28: BONLY00027 | L28: REV-RETAIL | M28: Revenue Retail | N28: 45865 | O28: 696.39 | P28: USD | Q28: IN | R28: CC300 | S28: CustC | T28: Misc receipt | U28: 3000 | V28: FALSE | Y28: UNMATCHED_B
B29: BONLY00028 | L29: AP-VENDOR | M29: Subledger AP | N29: 45900 | O29: 292.47 | P29: USD | Q29: DE | R29: CC400 | S29: CustA | T29: Misc receipt | U29: 2000 | V29: FALSE | Y29: UNMATCHED_B
B30: BONLY00029 | L30: REV-RETAIL | M30: Revenue Retail | N30: 45915 | O30: 408.44 | P30: USD | Q30: UK | R30: CC100 | S30: VendX | T30: Bank fee | U30: 3000 | V30: FALSE | Y30: UNMATCHED_B
... B36: BONLY00035 | L36: OPEX-MKT | M36: Operating Marketing | N36: 45899 | O36: -205.96 | P36: USD | Q36: UK | R36: CC100 | S36: VendY | T36: Misc receipt | U36: 5000 | V36: FALSE | Y36: UNMATCHED_B
B37: BONLY00036 | L37: MISC-INC | M37: Misc Income | N37: 45893 | O37: -578.01 | P37: USD | Q37: US | R37: CC400 | T37: Chargeback | U37: 6000 | V37: FALSE | Y37: UNMATCHED_B
B38: BONLY00037 | L38: REV-RETAIL | M38: Revenue Retail | N38: 45857 | O38: -413.72 | P38: USD | Q38: UK | R38: CC100 | S38: CustA | T38: Late fee | U38: 3000 | V38: FALSE | Y38: UNMATCHED_B
B39: BONLY00038 | L39: AP-VENDOR | M39: Subledger AP | N39: 45885 | O39: 264.33 | P39: USD | Q39: DE | R39: CC300 | S39: CustB | T39: Bank fee | U39: 2000 | V39: FALSE | Y39: UNMATCHED_B
B40: BONLY00039 | L40: AP-VENDOR | M40: Subledger AP | N40: 45904 | O40: 768.94 | P40: USD | Q40: US | R40: CC400 | S40: VendX | T40: Misc receipt | U40: 2000 | V40: FALSE | Y40: UNMATCHED_B
B41: BONLY00040 | L41: REV-RETAIL | M41: Revenue Retail | N41: 45897 | O41: 290.96 | P41: USD | Q41: DE | R41: CC200 | S41: CustA | T41: Chargeback | U41: 3000 | V41: FALSE | Y41: UNMATCHED_B

Sheet Mismatched_Amount
A1: doc_id | B1: ref_id | C1: gl_account | D1: gl_account_name | E1: posting_date | F1: amount_A | G1: currency_A | H1: entity_A | I1: cost_center_A | J1: counterparty_A | K1: memo | L1: source_account | M1: source_account_name | N1: txn_date | O1: amount_B | P1: currency_B | Q1: entity_B | R1: cost_center_B | S1: counterparty_B | T1: description | U1: mapped_gl_account | V1: mapping_ok | W1: amount_diff | X1: days_diff | Y1: status
A2: TXN000001 | B2: TXN000001 | C2: 2000 | D2: Accounts Payable | E2: 45917 | F2: -922.63 | G2: USD | H2: US | I2: CC100 | K2: Subscription | L2: AP-VENDOR | M2: Subledger AP | N2: 45919 | O2: -913.31 | P2: USD | Q2: US | R2: CC100 | T2: Subscription | U2: 2000 | V2: TRUE | W2: -9.32 | X2: -2 | Y2: MISMATCH
A3: TXN000004 | B3: TXN000004 | C3: 1000 | D3: Cash | E3: 45917 | F3: -601.88 | G3: USD | H3: US | I3: CC400 | J3: CustA | K3: Adjustment | L3: BANK-SAV | M3: Bank Savings | N3: 45915 | O3: -594.58 | P3: USD | Q3: US | R3: CC400 | S3: CustA | T3: Adjustment | U3: 1000 | V3: TRUE | W3: -7.3 | X3: 2 | Y3: MISMATCH
A4: TXN000014 | B4: TXN000014 | C4: 3000 | D4: Revenue | E4: 45887 | F4: 434.66 | G4: USD | H4: US | I4: CC100 | J4: VendZ | K4: Refund | L4: REV-RETAIL | M4: Revenue Retail | N4: 45890 | O4: 446.39 | P4: USD | Q4: US | R4: CC100 | S4: VendZ | T4: Refund | U4: 3000 | V4: TRUE | W4: -11.73 | X4: -3 | Y4: MISMATCH
A5: TXN000017 | B5: TXN000017 | C5: 5000 | D5: Operating Expense | E5: 45860 | F5: -638.65 | G5: USD | H5: DE | I5: CC200 | J5: VendZ | K5: Adjustment | L5: OPEX-MKT | M5: Operating Marketing | N5: 45859 | O5: -631.24 | P5: USD | Q5: DE | R5: CC200 | S5: VendZ | T5: Adjustment | U5: 5000 | V5: TRUE | W5: -7.41 | X5: 1 | Y5: MISMATCH
A6: TXN000030 | B6: TXN000030 | C6: 2000 | D6: Accounts Payable | E6: 45904 | F6: -395.88 | G6: USD | H6: UK | I6: CC100 | J6: CustB | K6: Subscription | L6: AP-VENDOR | M6: Subledger AP | N6: 45902 | O6: -393.87 | P6: USD | Q6: UK | R6: CC100 | S6: CustB | T6: Subscription | U6: 2000 | V6: TRUE | W6: -2.01 | X6: 2 | Y6: MISMATCH
A7: TXN000061 | B7: TXN000061 | C7: 3000 | D7: Revenue | E7: 45913 | F7: -407.8 | G7: USD | H7: DE | I7: CC300 | J7: CustA | L7: REV-ONLINE | M7: Revenue Online | N7: 45914 | O7: -406.08 | P7: USD | Q7: DE | R7: CC300 | S7: CustA | U7: 3000 | V7: TRUE | W7: -1.72 | X7: -1 | Y7: MISMATCH
A8: TXN000066 | B8: TXN000066 | C8: 1000 | D8: Cash | E8: 45886 | F8: -277.54 | G8: USD | H8: IN | I8: CC300 | J8: VendY | K8: Adjustment | L8: BANK-SAV | M8: Bank Savings | N8: 45888 | O8: -272.59 | P8: USD | Q8: IN | R8: CC300 | S8: VendY | T8: Adjustment | U8: 1000 | V8: TRUE | W8: -4.95 | X8: -2 | Y8: MISMATCH
A9: TXN000080 | B9: TXN000080 | C9: 1000 | D9: Cash | E9: 45866 | F9: -55.5 | G9: USD | H9: US | I9: CC400 | J9: CustA | K9: Invoice settlement | L9: BANK-SAV | M9: Bank Savings | N9: 45867 | O9: -46.61 | P9: USD | Q9: US | R9: CC400 | S9: CustA | T9: Invoice settlement | U9: 1000 | V9: TRUE | W9: -8.89 | X9: -1 | Y9: MISMATCH
A10: TXN000082 | B10: TXN000082 | C10: 5000 | D10: Operating Expense | E10: 45866 | F10: -723.59 | G10: USD | H10: UK | I10: CC100 | L10: OPEX-MKT | M10: Operating Marketing | N10: 45869 | O10: -719.22 | P10: USD | Q10: UK | R10: CC100 | U10: 5000 | V10: TRUE | W10: -4.37 | X10: -3 | Y10: MISMATCH
A11: TXN000095 | B11: TXN000095 | C11: 3000 | D11: Revenue | E11: 45862 | F11: 331.59 | G11: USD | H11: US | I11: CC300 | J11: VendX | K11: Monthly activity | L11: REV-RETAIL | M11: Revenue Retail | N11: 45860 | O11: 344.27 | P11: USD | Q11: US | R11: CC300 | S11: VendX | T11: Monthly activity | U11: 3000 | V11: TRUE | W11: -12.68 | X11: 2 | Y11: MISMATCH
A12: TXN000099 | B12: TXN000099 | C12: 4000 | D12: COGS | E12: 45858 | F12: -414.47 | G12: USD | H12: IN | I12: CC400 | J12: VendX | K12: Invoice settlement | L12: COGS-INV | M12: COGS Inventory | N12: 45861 | O12: -403.37 | P12: USD | Q12: IN | R12: CC400 | S12: VendX | T12: Invoice settlement | U12: 4000 | V12: TRUE | W12: -11.1 | X12: -3 | Y12: MISMATCH
A13: TXN000103 | B13: TXN000103 | C13: 4000 | D13: COGS | E13: 45912 | F13: 597.89 | G13: USD | H13: DE | I13: CC400 | K13: Invoice settlement | L13: COGS-INV | M13: COGS Inventory | N13: 45911 | O13: 604.93 | P13: USD | Q13: DE | R13: CC400 | T13: Invoice settlement | U13: 4000 | V13: TRUE | W13: -7.04 | X13: 1 | Y13: MISMATCH
A14: TXN000105 | B14: TXN000105 | C14: 4000 | D14: COGS | E14: 45889 | F14: -621.58 | G14: USD | H14: DE | I14: CC400 | J14: CustA | L14: COGS-INV | M14: COGS Inventory | N14: 45890 | O14: -614.62 | P14: USD | Q14: DE | R14: CC400 | S14: CustA | U14: 4000 | V14: TRUE | W14: -6.96 | X14: -1 | Y14: MISMATCH
A15: TXN000109 | B15: TXN000109 | C15: 3000 | D15: Revenue | E15: 45904 | F15: 929.43 | G15: USD | H15: DE | I15: CC400 | J15: VendZ | K15: Adjustment | L15: REV-RETAIL | M15: Revenue Retail | N15: 45905 | O15: 938.36 | P15: USD | Q15: DE | R15: CC400 | S15: VendZ | T15: Adjustment | U15: 3000 | V15: TRUE | W15: -8.93 | X15: -1 | Y15: MISMATCH
A16: TXN000126 | B16: TXN000126 | C16: 3000 | D16: Revenue | E16: 45860 | F16: -695.33 | G16: USD | H16: IN | I16: CC400 | J16: CustA | K16: Invoice settlement | L16: REV-RETAIL | M16: Revenue Retail | N16: 45858 | O16: -685.77 | P16: USD | Q16: IN | R16: CC400 | S16: CustA | T16: Invoice settlement | U16: 3000 | V16: TRUE | W16: -9.56 | X16: 2 | Y16: MISMATCH
A17: TXN000129 | B17: TXN000129 | C17: 3000 | D17: Revenue | E17: 45904 | F17: 741.05 | G17: USD | H17: US | I17: CC200 | J17: VendX | K17: Adjustment | L17: REV-RETAIL | M17: Revenue Retail | N17: 45905 | O17: 748.65 | P17: USD | Q17: US | R17: CC200 | S17: VendX | T17: Adjustment | U17: 3000 | V17: TRUE | W17: -7.6 | X17: -1 | Y17: MISMATCH
A18: TXN000131 | B18: TXN000131 | C18: 3000 | D18: Revenue | E18: 45863 | F18: 345.77 | G18: USD | H18: IN | I18: CC200 | J18: CustB | K18: Card fees | L18: REV-RETAIL | M18: Revenue Retail | N18: 45862 | O18: 346.84 | P18: USD | Q18: IN | R18: CC200 | S18: CustB | T18: Card fees | U18: 3000 | V18: TRUE | W18: -1.07 | X18: 1 | Y18: MISMATCH
A19: TXN000132 | B19: TXN000132 | C19: 4000 | D19: COGS | E19: 45915 | F19: 409.43 | G19: USD | H19: UK | I19: CC400 | J19: CustA | K19: Adjustment | L19: COGS-INV | M19: COGS Inventory | N19: 45917 | O19: 413.17 | P19: USD | Q19: UK | R19: CC400 | S19: CustA | T19: Adjustment | U19: 4000 | V19: TRUE | W19: -3.74 | X19: -2 | Y19: MISMATCH
A20: TXN000152 | B20: TXN000152 | C20: 1100 | D20: Accounts Receivable | E20: 45883 | F20: 51.59 | G20: USD | H20: UK | I20: CC100 | L20: AR-CUST | M20: Subledger AR | N20: 45881 | O20: 62.68 | P20: USD | Q20: UK | R20: CC100 | U20: 1100 | V20: TRUE | W20: -11.09 | X20: 2 | Y20: MISMATCH
A21: TXN000162 | B21: TXN000162 | C21: 3000 | D21: Revenue | E21: 45909 | F21: -602.95 | G21: USD | H21: DE | I21: CC400 | J21: VendZ | K21: Invoice settlement | L21: REV-ONLINE | M21: Revenue Online | N21: 45908 | O21: -584.4 | P21: USD | Q21: DE | R21: CC400 | S21: VendZ | T21: Invoice settlement | U21: 3000 | V21: TRUE | W21: -18.55 | X21: 1 | Y21: MISMATCH
A22: TXN000163 | B22: TXN000163 | C22: 1100 | D22: Accounts Receivable | E22: 45896 | F22: -965.01 | G22: USD | H22: UK | I22: CC100 | K22: Card fees | L22: AR-CUST | M22: Subledger AR | N22: 45894 | O22: -949.08 | P22: USD | Q22: UK | R22: CC100 | T22: Card fees | U22: 1100 | V22: TRUE | W22: -15.93 | X22: 2 | Y22: MISMATCH
A23: TXN000174 | B23: TXN000174 | C23: 6000 | D23: Other Income | E23: 45916 | F23: 738.53 | G23: USD | H23: US | I23: CC200 | J23: VendZ | L23: MISC-INC | M23: Misc Income | N23: 45917 | O23: 737.16 | P23: USD | Q23: US | R23: CC200 | S23: VendZ | U23: 6000 | V23: TRUE | W23: 1.37 | X23: -1 | Y23: MISMATCH
A24: TXN000177 | B24: TXN000177 | C24: 1100 | D24: Accounts Receivable | E24: 45872 | F24: 740.27 | G24: USD | H24: UK | I24: CC100 | J24: VendY | L24: AR-CUST | M24: Subledger AR | N24: 45871 | O24: 747.94 | P24: USD | Q24: UK | R24: CC100 | S24: VendY | U24: 1100 | V24: TRUE | W24: -7.67 | X24: 1 | Y24: MISMATCH
A25: TXN000181 | B25: TXN000181 | C25: 1100 | D25: Accounts Receivable | E25: 45858 | F25: -380.4 | G25: USD | H25: IN | I25: CC400 | J25: CustB | K25: Card fees | L25: AR-CUST | M25: Subledger AR | N25: 45858 | O25: -381.78 | P25: USD | Q25: IN | R25: CC400 | S25: CustB | T25: Card fees | U25: 1100 | V25: TRUE | W25: 1.38 | X25: 0 | Y25: MISMATCH
A26: TXN000197 | B26: TXN000197 | C26: 6000 | D26: Other Income | E26: 45904 | F26: 22.31 | G26: USD | H26: DE | I26: CC300 | J26: CustC | K26: Refund | L26: MISC-INC | M26: Misc Income | N26: 45902 | O26: 28.37 | P26: USD | Q26: DE | R26: CC300 | S26: CustC | T26: Refund | U26: 6000 | V26: TRUE | W26: -6.06 | X26: 2 | Y26: MISMATCH
A27: TXN000199 | B27: TXN000199 | C27: 3000 | D27: Revenue | E27: 45866 | F27: -734.71 | G27: USD | H27: IN | I27: CC400 | J27: VendY | K27: Invoice settlement | L27: REV-ONLINE | M27: Revenue Online | N27: 45868 | O27: -725.79 | P27: USD | Q27: IN | R27: CC400 | S27: VendY | T27: Invoice settlement | U27: 3000 | V27: TRUE | W27: -8.92 | X27: -2 | Y27: MISMATCH
A28: TXN000204 | B28: TXN000204 | C28: 1100 | D28: Accounts Receivable | E28: 45912 | F28: 164.09 | G28: USD | H28: DE | I28: CC400 | K28: Invoice settlement | L28: AR-CUST | M28: Subledger AR | N28: 45910 | O28: 169.47 | P28: USD | Q28: DE | R28: CC400 | T28: Invoice settlement | U28: 1100 | V28: TRUE | W28: -5.38 | X28: 2 | Y28: MISMATCH
A29: TXN000220 | B29: TXN000220 | C29: 1000 | D29: Cash | E29: 45858 | F29: -648.1 | G29: USD | H29: US | I29: CC100 | J29: VendZ | K29: Monthly activity | L29: BANK-CHK | M29: Bank Checking | N29: 45858 | O29: -649.43 | P29: USD | Q29: US | R29: CC100 | S29: VendZ | T29: Monthly activity | U29: 1000 | V29: TRUE | W29: 1.33 | X29: 0 | Y29: MISMATCH
A30: TXN000222 | B30: TXN000222 | C30: 5000 | D30: Operating Expense | E30: 45914 | F30: 935.09 | G30: USD | H30: IN | I30: CC100 | J30: CustB | K30: Adjustment | L30: OPEX-IT | M30: Operating IT | N30: 45913 | O30: 945.43 | P30: USD | Q30: IN | R30: CC100 | S30: CustB | T30: Adjustment | U30: 5000 | V30: TRUE | W30: -10.34 | X30: 1 | Y30: MISMATCH
A31: TXN000227 | B31: TXN000227 | C31: 1000 | D31: Cash | E31: 45907 | F31: 670.71 | G31: USD | H31: IN | I31: CC100 | J31: CustC | K31: Card fees | L31: BANK-CHK | M31: Bank Checking | N31: 45905 | O31: 672.32 | P31: USD | Q31: IN | R31: CC100 | S31: CustC | T31: Card fees | U31: 1000 | V31: TRUE | W31: -1.61 | X31: 2 | Y31: MISMATCH
A32: TXN000242 | B32: TXN000242 | C32: 3000 | D32: Revenue | E32: 45881 | F32: -25.03 | G32: USD | H32: UK | I32: CC300 | J32: VendZ | K32: Invoice settlement | L32: REV-ONLINE | M32: Revenue Online | N32: 45880 | O32: -23.96 | P32: USD | Q32: UK | R32: CC300 | S32: VendZ | T32: Invoice settlement | U32: 3000 | V32: TRUE | W32: -1.07 | X32: 1 | Y32: MISMATCH
A33: TXN000251 | B33: TXN000251 | C33: 1000 | D33: Cash | E33: 45881 | F33: 458.26 | G33: USD | H33: US | I33: CC100 | J33: CustC | K33: Subscription | L33: BANK-CHK | M33: Bank Checking | N33: 45879 | O33: 461.5 | P33: USD | Q33: US | R33: CC100 | S33: CustC | T33: Subscription | U33: 1000 | V33: TRUE | W33: -3.24 | X33: 2 | Y33: MISMATCH
A34: TXN000252 | B34: TXN000252 | C34: 3000 | D34: Revenue | E34: 45867 | F34: 442.55 | G34: USD | H34: UK | I34: CC300 | J34: CustA | L34: REV-ONLINE | M34: Revenue Online | N34: 45869 | O34: 444.71 | P34: USD | Q34: UK | R34: CC300 | S34: CustA | U34: 3000 | V34: TRUE | W34: -2.16 | X34: -2 | Y34: MISMATCH
A35: TXN000257 | B35: TXN000257 | C35: 4000 | D35: COGS | E35: 45897 | F35: 382.96 | G35: USD | H35: DE | I35: CC300 | J35: CustA | K35: Adjustment | L35: COGS-INV | M35: COGS Inventory | N35: 45895 | O35: 395.64 | P35: USD | Q35: DE | R35: CC300 | S35: CustA | T35: Adjustment | U35: 4000 | V35: TRUE | W35: -12.68 | X35: 2 | Y35: MISMATCH
A36: TXN000275 | B36: TXN000275 | C36: 5000 | D36: Operating Expense | E36: 45901 | F36: 651.16 | G36: USD | H36: DE | I36: CC400 | J36: CustC | K36: Card fees | L36: OPEX-MKT | M36: Operating Marketing | N36: 45903 | O36: 655.37 | P36: USD | Q36: DE | R36: CC400 | S36: CustC | T36: Card fees | U36: 5000 | V36: TRUE | W36: -4.21 | X36: -2 | Y36: MISMATCH
A37: TXN000277 | B37: TXN000277 | C37: 1000 | D37: Cash | E37: 45900 | F37: 357.89 | G37: USD | H37: DE | I37: CC100 | J37: VendY | K37: Card fees | L37: BANK-CHK | M37: Bank Checking | N37: 45899 | O37: 356.04 | P37: USD | Q37: DE | R37: CC100 | S37: VendY | T37: Card fees | U37: 1000 | V37: TRUE | W37: 1.85 | X37: 1 | Y37: MISMATCH
A38: TXN000284 | B38: TXN000284 | C38: 1100 | D38: Accounts Receivable | E38: 45894 | F38: 444.26 | G38: USD | H38: US | I38: CC100 | J38: VendX | K38: Refund | L38: AR-CUST | M38: Subledger AR | N38: 45897 | O38: 446.19 | P38: USD | Q38: US | R38: CC100 | S38: VendX | T38: Refund | U38: 1100 | V38: TRUE | W38: -1.93 | X38: -3 | Y38: MISMATCH
A39: TXN000294 | B39: TXN000294 | C39: 5000 | D39: Operating Expense | E39: 45863 | F39: -262.2 | G39: USD | H39: IN | I39: CC200 | J39: CustB | K39: Refund | L39: OPEX-IT | M39: Operating IT | N39: 45866 | O39: -254.48 | P39: USD | Q39: IN | R39: CC200 | S39: CustB | T39: Refund | U39: 5000 | V39: TRUE | W39: -7.72 | X39: -3 | Y39: MISMATCH
A40: TXN000295 | B40: TXN000295 | C40: 1000 | D40: Cash | E40: 45884 | F40: -394.93 | G40: USD | H40: US | I40: CC100 | J40: CustB | L40: BANK-CHK | M40: Bank Checking | N40: 45882 | O40: -387.63 | P40: USD | Q40: US | R40: CC100 | S40: CustB | U40: 1000 | V40: TRUE | W40: -7.3 | X40: 2 | Y40: MISMATCH

Sheet Mapping
A1: source_account | B1: gl_account
A2: BANK-CHK | B2: 1000
A3: BANK-SAV | B3: 1000
A4: AR-CUST | B4: 1100
A5: REV-ONLINE | B5: 3000
A6: REV-RETAIL | B6: 3000
A7: AP-VENDOR | B7: 2000
A8: COGS-INV | B8: 4000
A9: OPEX-MKT | B9: 5000
A10: OPEX-IT | B10: 5000
A11: MISC-INC | B11: 6000

Sheet ExceptionsByGL
A1: gl_account | B1: exceptions_count
A2: 3000 | B2: 14
A3: 1000 | B3: 12
A4: 4000 | B4: 10
A5: 2100 | B5: 9
A6: 5000 | B6: 8
A7: 6000 | B7: 8
A8: 2000 | B8: 7
A9: 1100 | B9: 6
A10: 7000 | B10: 3
A11: 1200 | B11: 2

Sheet ExceptionsBySrc
A1: source_account | B1: exceptions_count
A2: REV-RETAIL | B2: 12
A3: AR-CUST | B3: 9
A4: BANK-CHK | B4: 9
A5: COGS-INV | B5: 9
A6: OPEX-MKT | B6: 9
A7: AP-VENDOR | B7: 8
A8: BANK-SAV | B8: 8
A9: REV-ONLINE | B9: 8
A10: OPEX-IT | B10: 4
A11: MISC-INC | B11: 3

Sheet Model
A1: doc_id | B1: ref_id | C1: gl_account | D1: gl_account_name | E1: posting_date | F1: amount_A | G1: currency_A | H1: entity_A | I1: cost_center_A | J1: counterparty_A | K1: memo | L1: source_account | M1: source_account_name | N1: txn_date | O1: amount_B | P1: currency_B | Q1: entity_B | R1: cost_center_B | S1: counterparty_B | T1: description | U1: mapped_gl_account | V1: mapping_ok | W1: amount_diff | X1: days_diff | Y1: status
A2: TXN000001 | B2: TXN000001 | C2: 2000 | D2: Accounts Payable | E2: 45917 | F2: -922.63 | G2: USD | H2: US | I2: CC100 | K2: Subscription | L2: AP-VENDOR | M2: Subledger AP | N2: 45919 | O2: -913.31 | P2: USD | Q2: US | R2: CC100 | T2: Subscription | U2: 2000 | V2: TRUE | W2: -9.32 | X2: -2 | Y2: MISMATCH
A3: TXN000002 | B3: TXN000002 | C3: 1000 | D3: Cash | E3: 45880 | F3: 383.52 | G3: USD | H3: UK | I3: CC100 | J3: CustA | K3: Card fees | L3: BANK-SAV | M3: Bank Savings | N3: 45880 | O3: 383.52 | P3: USD | Q3: UK | R3: CC100 | S3: CustA | T3: Card fees | U3: 1000 | V3: TRUE | W3: 0 | X3: 0 | Y3: EXACT_MATCH
A4: TXN000003 | B4: TXN000003 | C4: 4000 | D4: COGS | E4: 45861 | F4: -508.21 | G4: USD | H4: IN | I4: CC100 | K4: Subscription | L4: COGS-INV | M4: COGS Inventory | N4: 45861 | O4: -508.21 | P4: USD | Q4: IN | R4: CC100 | T4: Subscription | U4: 4000 | V4: TRUE | W4: 0 | X4: 0 | Y4: EXACT_MATCH
A5: TXN000004 | B5: TXN000004 | C5: 1000 | D5: Cash | E5: 45917 | F5: -601.88 | G5: USD | H5: US | I5: CC400 | J5: CustA | K5: Adjustment | L5: BANK-SAV | M5: Bank Savings | N5: 45915 | O5: -594.58 | P5: USD | Q5: US | R5: CC400 | S5: CustA | T5: Adjustment | U5: 1000 | V5: TRUE | W5: -7.3 | X5: 2 | Y5: MISMATCH
A6: TXN000005 | B6: TXN000005 | C6: 1000 | D6: Cash | E6: 45892 | F6: 302.77 | G6: USD | H6: DE | I6: CC400 | J6: CustB | K6: Subscription | L6: BANK-CHK | M6: Bank Checking | N6: 45892 | O6: 302.77 | P6: USD | Q6: DE | R6: CC400 | S6: CustB | T6: Subscription | U6: 1000 | V6: TRUE | W6: 0 | X6: 0 | Y6: EXACT_MATCH
A7: TXN000006 | B7: TXN000006 | C7: 1000 | D7: Cash | E7: 45893 | F7: -500.52 | G7: USD | H7: UK | I7: CC100 | J7: VendY | K7: Subscription | L7: BANK-SAV | M7: Bank Savings | N7: 45893 | O7: -500.52 | P7: USD | Q7: UK | R7: CC100 | S7: VendY | T7: Subscription | U7: 1000 | V7: TRUE | W7: 0 | X7: 0 | Y7: EXACT_MATCH
A8: TXN000007 | B8: TXN000007 | C8: 3000 | D8: Revenue | E8: 45880 | F8: -499.78 | G8: USD | H8: US | I8: CC100 | J8: VendY | K8: Adjustment | L8: REV-ONLINE | M8: Revenue Online | N8: 45880 | O8: -499.78 | P8: USD | Q8: US | R8: CC100 | S8: VendY | T8: Adjustment | U8: 3000 | V8: TRUE | W8: 0 | X8: 0 | Y8: EXACT_MATCH
A9: TXN000008 | B9: TXN000008 | C9: 5000 | D9: Operating Expense | E9: 45900 | F9: 61.32 | G9: USD | H9: DE | I9: CC400 | J9: VendY | K9: Card fees | L9: OPEX-MKT | M9: Operating Marketing | N9: 45900 | O9: 61.32 | P9: USD | Q9: DE | R9: CC400 | S9: VendY | T9: Card fees | U9: 5000 | V9: TRUE | W9: 0 | X9: 0 | Y9: EXACT_MATCH
A10: TXN000009 | B10: TXN000009 | C10: 2000 | D10: Accounts Payable | E10: 45876 | F10: -754.41 | G10: USD | H10: UK | I10: CC200 | J10: CustA | K10: Subscription | L10: AP-VENDOR | M10: Subledger AP | N10: 45876 | O10: -754.41 | P10: USD | Q10: UK | R10: CC200 | S10: CustA | T10: Subscription | U10: 2000 | V10: TRUE | W10: 0 | X10: 0 | Y10: EXACT_MATCH
A11: TXN000010 | B11: TXN000010 | C11: 3000 | D11: Revenue | E11: 45890 | F11: 650.12 | G11: USD | H11: DE | I11: CC400 | J11: CustC | K11: Subscription | L11: REV-RETAIL | M11: Revenue Retail | N11: 45891 | O11: 649.17 | P11: USD | Q11: DE | R11: CC400 | S11: CustC | T11: Subscription | U11: 3000 | V11: TRUE | W11: 0.95 | X11: -1 | Y11: NEAR_MATCH
A12: TXN000011 | B12: TXN000011 | C12: 1000 | D12: Cash | E12: 45864 | F12: 343.64 | G12: USD | H12: UK | I12: CC300 | J12: CustB | K12: Card fees | L12: BANK-SAV | M12: Bank Savings | N12: 45865 | O12: 343.79 | P12: USD | Q12: UK | R12: CC300 | S12: CustB | T12: Card fees | U12: 1000 | V12: TRUE | W12: -0.15 | X12: -1 | Y12: NEAR_MATCH
A13: TXN000012 | B13: TXN000012 | C13: 4000 | D13: COGS | E13: 45859 | F13: 457.11 | G13: USD | H13: US | I13: CC300 | J13: CustC | K13: Refund | L13: COGS-INV | M13: COGS Inventory | N13: 45859 | O13: 457.11 | P13: USD | Q13: US | R13: CC300 | S13: CustC | T13: Refund | U13: 4000 | V13: TRUE | W13: 0 | X13: 0 | Y13: EXACT_MATCH
A14: TXN000013 | B14: TXN000013 | C14: 2000 | D14: Accounts Payable | E14: 45895 | F14: 626.32 | G14: USD | H14: IN | I14: CC100 | K14: Monthly activity | L14: AP-VENDOR | M14: Subledger AP | N14: 45895 | O14: 626.32 | P14: USD | Q14: IN | R14: CC100 | T14: Monthly activity | U14: 2000 | V14: TRUE | W14: 0 | X14: 0 | Y14: EXACT_MATCH
A15: TXN000014 | B15: TXN000014 | C15: 3000 | D15: Revenue | E15: 45887 | F15: 434.66 | G15: USD | H15: US | I15: CC100 | J15: VendZ | K15: Refund | L15: REV-RETAIL | M15: Revenue Retail | N15: 45890 | O15: 446.39 | P15: USD | Q15: US | R15: CC100 | S15: VendZ | T15: Refund | U15: 3000 | V15: TRUE | W15: -11.73 | X15: -3 | Y15: MISMATCH
A16: TXN000015 | B16: TXN000015 | C16: 3000 | D16: Revenue | E16: 45898 | F16: 439.31 | G16: USD | H16: IN | I16: CC300 | J16: VendZ | K16: Card fees | L16: REV-RETAIL | M16: Revenue Retail | N16: 45898 | O16: 439.31 | P16: USD | Q16: IN | R16: CC300 | S16: VendZ | T16: Card fees | U16: 3000 | V16: TRUE | W16: 0 | X16: 0 | Y16: EXACT_MATCH
A17: TXN000016 | B17: TXN000016 | C17: 2000 | D17: Accounts Payable | E17: 45858 | F17: 136.69 | G17: USD | H17: DE | I17: CC200 | J17: VendY | K17: Monthly activity | L17: AP-VENDOR | M17: Subledger AP | N17: 45858 | O17: 136.69 | P17: USD | Q17: DE | R17: CC200 | S17: VendY | T17: Monthly activity | U17: 2000 | V17: TRUE | W17: 0 | X17: 0 | Y17: EXACT_MATCH
A18: TXN000017 | B18: TXN000017 | C18: 5000 | D18: Operating Expense | E18: 45860 | F18: -638.65 | G18: USD | H18: DE | I18: CC200 | J18: VendZ | K18: Adjustment | L18: OPEX-MKT | M18: Operating Marketing | N18: 45859 | O18: -631.24 | P18: USD | Q18: DE | R18: CC200 | S18: VendZ | T18: Adjustment | U18: 5000 | V18: TRUE | W18: -7.41 | X18: 1 | Y18: MISMATCH
A19: TXN000018 | B19: TXN000018 | C19: 4000 | D19: COGS | E19: 45882 | F19: 530.97 | G19: USD | H19: IN | I19: CC100 | J19: CustB | K19: Card fees | L19: COGS-INV | M19: COGS Inventory | N19: 45882 | O19: 530.97 | P19: USD | Q19: IN | R19: CC100 | S19: CustB | T19: Card fees | U19: 4000 | V19: TRUE | W19: 0 | X19: 0 | Y19: EXACT_MATCH
A20: TXN000019 | B20: TXN000019 | C20: 4000 | D20: COGS | E20: 45892 | F20: -568.61 | G20: USD | H20: UK | I20: CC400 | K20: Subscription | L20: COGS-INV | M20: COGS Inventory | N20: 45892 | O20: -568.61 | P20: USD | Q20: UK | R20: CC400 | T20: Subscription | U20: 4000 | V20: TRUE | W20: 0 | X20: 0 | Y20: EXACT_MATCH
A21: TXN000020 | B21: TXN000020 | C21: 3000 | D21: Revenue | E21: 45902 | F21: 118.37 | G21: USD | H21: DE | I21: CC400 | J21: CustB | K21: Adjustment | L21: REV-RETAIL | M21: Revenue Retail | N21: 45902 | O21: 118.37 | P21: USD | Q21: DE | R21: CC400 | S21: CustB | T21: Adjustment | U21: 3000 | V21: TRUE | W21: 0 | X21: 0 | Y21: EXACT_MATCH
A22: TXN000021 | B22: TXN000021 | C22: 1000 | D22: Cash | E22: 45868 | F22: -912.67 | G22: USD | H22: UK | I22: CC100 | J22: VendX | L22: BANK-SAV | M22: Bank Savings | N22: 45870 | O22: -912.71 | P22: USD | Q22: UK | R22: CC100 | S22: VendX | U22: 1000 | V22: TRUE | W22: 0.04 | X22: -2 | Y22: NEAR_MATCH
A23: TXN000022 | B23: TXN000022 | C23: 6000 | D23: Other Income | E23: 45868 | F23: -538.58 | G23: USD | H23: US | I23: CC200 | J23: VendX | K23: Subscription | L23: MISC-INC | M23: Misc Income | N23: 45868 | O23: -538.58 | P23: USD | Q23: US | R23: CC200 | S23: VendX | T23: Subscription | U23: 6000 | V23: TRUE | W23: 0 | X23: 0 | Y23: EXACT_MATCH
A24: TXN000023 | B24: TXN000023 | C24: 2000 | D24: Accounts Payable | E24: 45896 | F24: 403.22 | G24: USD | H24: UK | I24: CC100 | J24: VendX | L24: AP-VENDOR | M24: Subledger AP | N24: 45896 | O24: 403.22 | P24: USD | Q24: UK | R24: CC100 | S24: VendX | U24: 2000 | V24: TRUE | W24: 0 | X24: 0 | Y24: EXACT_MATCH
A25: TXN000024 | B25: TXN000024 | C25: 5000 | D25: Operating Expense | E25: 45882 | F25: -1007.27 | G25: USD | H25: IN | I25: CC100 | J25: VendX | K25: Refund | L25: OPEX-IT | M25: Operating IT | N25: 45882 | O25: -1006.43 | P25: USD | Q25: IN | R25: CC100 | S25: VendX | T25: Refund | U25: 5000 | V25: TRUE | W25: -0.84 | X25: 0 | Y25: NEAR_MATCH
A26: TXN000025 | B26: TXN000025 | C26: 4000 | D26: COGS | E26: 45860 | F26: -488.65 | G26: USD | H26: UK | I26: CC400 | J26: CustB | K26: Monthly activity | L26: COGS-INV | M26: COGS Inventory | N26: 45861 | O26: -489.4 | P26: USD | Q26: UK | R26: CC400 | S26: CustB | T26: Monthly activity | U26: 4000 | V26: TRUE | W26: 0.75 | X26: -1 | Y26: NEAR_MATCH
A27: TXN000026 | B27: TXN000026 | C27: 2000 | D27: Accounts Payable | E27: 45895 | F27: -137.33 | G27: USD | H27: US | I27: CC200 | J27: VendY | K27: Monthly activity | L27: AP-VENDOR | M27: Subledger AP | N27: 45895 | O27: -137.33 | P27: USD | Q27: US | R27: CC200 | S27: VendY | T27: Monthly activity | U27: 2000 | V27: TRUE | W27: 0 | X27: 0 | Y27: EXACT_MATCH
A28: TXN000027 | B28: TXN000027 | C28: 2000 | D28: Accounts Payable | E28: 45896 | F28: -398.69 | G28: USD | H28: UK | I28: CC400 | J28: CustB | K28: Refund | L28: AP-VENDOR | M28: Subledger AP | N28: 45896 | O28: -398.69 | P28: USD | Q28: UK | R28: CC400 | S28: CustB | T28: Refund | U28: 2000 | V28: TRUE | W28: 0 | X28: 0 | Y28: EXACT_MATCH
A29: TXN000028 | B29: TXN000028 | C29: 3000 | D29: Revenue | E29: 45879 | F29: -72.08 | G29: USD | H29: IN | I29: CC100 | J29: CustA | L29: REV-RETAIL | M29: Revenue Retail | N29: 45879 | O29: -72.08 | P29: USD | Q29: IN | R29: CC100 | S29: CustA | U29: 3000 | V29: TRUE | W29: 0 | X29: 0 | Y29: EXACT_MATCH
A30: TXN000029 | B30: TXN000029 | C30: 5000 | D30: Operating Expense | E30: 45886 | F30: 762.35 | G30: USD | H30: DE | I30: CC100 | J30: CustB | K30: Monthly activity | L30: OPEX-MKT | M30: Operating Marketing | N30: 45886 | O30: 762.35 | P30: USD | Q30: DE | R30: CC100 | S30: CustB | T30: Monthly activity | U30: 5000 | V30: TRUE | W30: 0 | X30: 0 | Y30: EXACT_MATCH
A31: TXN000030 | B31: TXN000030 | C31: 2000 | D31: Accounts Payable | E31: 45904 | F31: -395.88 | G31: USD | H31: UK | I31: CC100 | J31: CustB | K31: Subscription | L31: AP-VENDOR | M31: Subledger AP | N31: 45902 | O31: -393.87 | P31: USD | Q31: UK | R31: CC100 | S31: CustB | T31: Subscription | U31: 2000 | V31: TRUE | W31: -2.01 | X31: 2 | Y31: MISMATCH
A32: TXN000031 | B32: TXN000031 | C32: 2000 | D32: Accounts Payable | E32: 45866 | F32: 314.36 | G32: USD | H32: US | I32: CC300 | J32: VendZ | L32: AP-VENDOR | M32: Subledger AP | N32: 45866 | O32: 314.36 | P32: USD | Q32: US | R32: CC300 | S32: VendZ | U32: 2000 | V32: TRUE | W32: 0 | X32: 0 | Y32: EXACT_MATCH
A33: TXN000032 | B33: TXN000032 | C33: 1000 | D33: Cash | E33: 45901 | F33: 768.12 | G33: USD | H33: DE | I33: CC200 | J33: CustC | L33: BANK-SAV | M33: Bank Savings | N33: 45901 | O33: 768.12 | P33: USD | Q33: DE | R33: CC200 | S33: CustC | U33: 1000 | V33: TRUE | W33: 0 | X33: 0 | Y33: EXACT_MATCH
A34: TXN000033 | B34: TXN000033 | C34: 3000 | D34: Revenue | E34: 45891 | F34: 87.23 | G34: USD | H34: DE | I34: CC200 | J34: VendY | L34: REV-ONLINE | M34: Revenue Online | N34: 45891 | O34: 86.84 | P34: USD | Q34: DE | R34: CC200 | S34: VendY | U34: 3000 | V34: TRUE | W34: 0.39 | X34: 0 | Y34: NEAR_MATCH
A35: TXN000034 | B35: TXN000034 | C35: 3000 | D35: Revenue | E35: 45908 | F35: -633.86 | G35: USD | H35: IN | I35: CC200 | J35: CustB | K35: Subscription | L35: REV-ONLINE | M35: Revenue Online | N35: 45908 | O35: -633.86 | P35: USD | Q35: IN | R35: CC200 | S35: CustB | T35: Subscription | U35: 3000 | V35: TRUE | W35: 0 | X35: 0 | Y35: EXACT_MATCH
A36: TXN000035 | B36: TXN000035 | C36: 5000 | D36: Operating Expense | E36: 45879 | F36: -16.1 | G36: USD | H36: US | I36: CC300 | J36: VendX | K36: Invoice settlement | L36: OPEX-MKT | M36: Operating Marketing | N36: 45881 | O36: -16.82 | P36: USD | Q36: US | R36: CC300 | S36: VendX | T36: Invoice settlement | U36: 5000 | V36: TRUE | W36: 0.72 | X36: -2 | Y36: NEAR_MATCH
A37: TXN000036 | B37: TXN000036 | C37: 3000 | D37: Revenue | E37: 45901 | F37: 334.46 | G37: USD | H37: DE | I37: CC400 | K37: Refund | L37: REV-ONLINE | M37: Revenue Online | N37: 45901 | O37: 334.46 | P37: USD | Q37: DE | R37: CC400 | T37: Refund | U37: 3000 | V37: TRUE | W37: 0 | X37: 0 | Y37: EXACT_MATCH
A38: TXN000037 | B38: TXN000037 | C38: 2000 | D38: Accounts Payable | E38: 45880 | F38: -198.95 | G38: USD | H38: US | I38: CC200 | J38: VendX | K38: Adjustment | L38: AP-VENDOR | M38: Subledger AP | N38: 45880 | O38: -198.95 | P38: USD | Q38: US | R38: CC200 | S38: VendX | T38: Adjustment | U38: 2000 | V38: TRUE | W38: 0 | X38: 0 | Y38: EXACT_MATCH
A39: TXN000038 | B39: TXN000038 | C39: 2000 | D39: Accounts Payable | E39: 45870 | F39: 865.49 | G39: USD | H39: US | I39: CC400 | J39: VendZ | K39: Invoice settlement | L39: AP-VENDOR | M39: Subledger AP | N39: 45870 | O39: 865.49 | P39: USD | Q39: US | R39: CC400 | S39: VendZ | T39: Invoice settlement | U39: 2000 | V39: TRUE | W39: 0 | X39: 0 | Y39: EXACT_MATCH
A40: TXN000039 | B40: TXN000039 | C40: 1000 | D40: Cash | E40: 45910 | F40: 941.54 | G40: USD | H40: IN | I40: CC200 | J40: VendX | K40: Adjustment | L40: BANK-SAV | M40: Bank Savings | N40: 45910 | O40: 942.35 | P40: USD | Q40: IN | R40: CC200 | S40: VendX | T40: Adjustment | U40: 1000 | V40: TRUE | W40: -0.81 | X40: 0 | Y40: NEAR_MATCH
A41: TXN000040 | B41: TXN000040 | C41: 4000 | D41: COGS | E41: 45907 | F41: 417.65 | G41: USD | H41: US | I41: CC400 | J41: VendX | K41: Card fees | L41: COGS-INV | M41: COGS Inventory | N41: 45907 | O41: 417.84 | P41: USD | Q41: US | R41: CC400 | S41: VendX | T41: Card fees | U41: 4000 | V41: TRUE | W41: -0.19 | X41: 0 | Y41: NEAR_MATCH
A42: TXN000041 | B42: TXN000041 | C42: 1000 | D42: Cash | E42: 45903 | F42: -710.18 | G42: USD | H42: UK | I42: CC100 | J42: CustB | K42: Subscription | L42: BANK-SAV | M42: Bank Savings | N42: 45903 | O42: -710.18 | P42: USD | Q42: UK | R42: CC100 | S42: CustB | T42: Subscription | U42: 1000 | V42: TRUE | W42: 0 | X42: 0 | Y42: EXACT_MATCH
A43: TXN000042 | B43: TXN000042 | C43: 5000 | D43: Operating Expense | E43: 45908 | F43: 455 | G43: USD | H43: IN | I43: CC300 | J43: CustB | K43: Subscription | L43: OPEX-MKT | M43: Operating Marketing | N43: 45908 | O43: 455 | P43: USD | Q43: IN | R43: CC300 | S43: CustB | T43: Subscription | U43: 5000 | V43: TRUE | W43: 0 | X43: 0 | Y43: EXACT_MATCH
A44: TXN000043 | B44: TXN000043 | C44: 5000 | D44: Operating Expense | E44: 45865 | F44: -642.02 | G44: USD | H44: US | I44: CC200 | J44: VendX | L44: OPEX-IT | M44: Operating IT | N44: 45865 | O44: -642.02 | P44: USD | Q44: US | R44: CC200 | S44: VendX | U44: 5000 | V44: TRUE | W44: 0 | X44: 0 | Y44: EXACT_MATCH
A45: TXN000044 | B45: TXN000044 | C45: 3000 | D45: Revenue | E45: 45909 | F45: 311.79 | G45: USD | H45: US | I45: CC300 | J45: CustB | K45: Invoice settlement | L45: REV-ONLINE | M45: Revenue Online | N45: 45910 | O45: 311.27 | P45: USD | Q45: US | R45: CC300 | S45: CustB | T45: Invoice settlement | U45: 3000 | V45: TRUE | W45: 0.52 | X45: -1 | Y45: NEAR_MATCH
A46: TXN000045 | B46: TXN000045 | C46: 5000 | D46: Operating Expense | E46: 45872 | F46: 72.92 | G46: USD | H46: DE | I46: CC300 | J46: VendY | K46: Card fees | L46: OPEX-IT | M46: Operating IT | N46: 45872 | O46: 72.92 | P46: USD | Q46: DE | R46: CC300 | S46: VendY | T46: Card fees | U46: 5000 | V46: TRUE | W46: 0 | X46: 0 | Y46: EXACT_MATCH
A47: TXN000046 | B47: TXN000046 | C47: 1100 | D47: Accounts Receivable | E47: 45860 | F47: 49.23 | G47: USD | H47: DE | I47: CC400 | J47: VendZ | K47: Subscription | L47: AR-CUST | M47: Subledger AR | N47: 45860 | O47: 49.23 | P47: USD | Q47: DE | R47: CC400 | S47: VendZ | T47: Subscription | U47: 1100 | V47: TRUE | W47: 0 | X47: 0 | Y47: EXACT_MATCH
A48: TXN000047 | B48: TXN000047 | C48: 5000 | D48: Operating Expense | E48: 45883 | F48: 595.78 | G48: USD | H48: UK | I48: CC200 | J48: VendY | K48: Subscription | L48: OPEX-IT | M48: Operating IT | N48: 45883 | O48: 595.78 | P48: USD | Q48: UK | R48: CC200 | S48: VendY | T48: Subscription | U48: 5000 | V48: TRUE | W48: 0 | X48: 0 | Y48: EXACT_MATCH
A49: TXN000048 | B49: TXN000048 | C49: 1000 | D49: Cash | E49: 45912 | F49: 1061.9 | G49: USD | H49: UK | I49: CC100 | L49: BANK-CHK | M49: Bank Checking | N49: 45912 | O49: 1061.9 | P49: USD | Q49: UK | R49: CC100 | U49: 1000 | V49: TRUE | W49: 0 | X49: 0 | Y49: EXACT_MATCH
A50: TXN000049 | B50: TXN000049 | C50: 1100 | D50: Accounts Receivable | E50: 45868 | F50: -567.35 | G50: USD | H50: US | I50: CC100 | J50: CustC | K50: Refund | L50: AR-CUST | M50: Subledger AR | N50: 45868 | O50: -567.35 | P50: USD | Q50: US | R50: CC100 | S50: CustC | T50: Refund | U50: 1100 | V50: TRUE | W50: 0 | X50: 0 | Y50: EXACT_MATCH
A51: TXN000050 | B51: TXN000050 | C51: 5000 | D51: Operating Expense | E51: 45890 | F51: 368.85 | G51: USD | H51: US | I51: CC100 | J51: CustB | K51: Adjustment | L51: OPEX-IT | M51: Operating IT | N51: 45890 | O51: 368.85 | P51: USD | Q51: US | R51: CC100 | S51: CustB | T51: Adjustment | U51: 5000 | V51: TRUE | W51: 0 | X51: 0 | Y51: EXACT_MATCH
A52: TXN000051 | B52: TXN000051 | C52: 3000 | D52: Revenue | E52: 45859 | F52: 978 | G52: USD | H52: IN | I52: CC100 | K52: Monthly activity | L52: REV-RETAIL | M52: Revenue Retail | N52: 45859 | O52: 978 | P52: USD | Q52: IN | R52: CC100 | T52: Monthly activity | U52: 3000 | V52: TRUE | W52: 0 | X52: 0 | Y52: EXACT_MATCH
A53: TXN000052 | B53: TXN000052 | C53: 5000 | D53: Operating Expense | E53: 45877 | F53: 559.33 | G53: USD | H53: UK | I53: CC300 | J53: VendX | K53: Subscription | L53: OPEX-MKT | M53: Operating Marketing | N53: 45877 | O53: 559.33 | P53: USD | Q53: UK | R53: CC300 | S53: VendX | T53: Subscription | U53: 5000 | V53: TRUE | W53: 0 | X53: 0 | Y53: EXACT_MATCH
A54: TXN000053 | B54: TXN000053 | C54: 5000 | D54: Operating Expense | E54: 45908 | F54: 525.36 | G54: USD | H54: UK | I54: CC300 | J54: VendY | K54: Adjustment | L54: OPEX-IT | M54: Operating IT | N54: 45908 | O54: 525.36 | P54: USD | Q54: UK | R54: CC300 | S54: VendY | T54: Adjustment | U54: 5000 | V54: TRUE | W54: 0 | X54: 0 | Y54: EXACT_MATCH
A55: TXN000054 | B55: TXN000054 | C55: 5000 | D55: Operating Expense | E55: 45865 | F55: 563.14 | G55: USD | H55: IN | I55: CC400 | J55: CustC | K55: Monthly activity | L55: OPEX-MKT | M55: Operating Marketing | N55: 45865 | O55: 563.14 | P55: USD | Q55: IN | R55: CC400 | S55: CustC | T55: Monthly activity | U55: 5000 | V55: TRUE | W55: 0 | X55: 0 | Y55: EXACT_MATCH
A56: TXN000055 | B56: TXN000055 | C56: 3000 | D56: Revenue | E56: 45884 | F56: -466.91 | G56: USD | H56: DE | I56: CC100 | K56: Adjustment | L56: REV-ONLINE | M56: Revenue Online | N56: 45885 | O56: -467.28 | P56: USD | Q56: DE | R56: CC100 | T56: Adjustment | U56: 3000 | V56: TRUE | W56: 0.37 | X56: -1 | Y56: NEAR_MATCH
A57: TXN000056 | B57: TXN000056 | C57: 2000 | D57: Accounts Payable | E57: 45866 | F57: -422.63 | G57: USD | H57: UK | I57: CC400 | J57: CustB | K57: Refund | L57: AP-VENDOR | M57: Subledger AP | N57: 45866 | O57: -422.63 | P57: USD | Q57: UK | R57: CC400 | S57: CustB | T57: Refund | U57: 2000 | V57: TRUE | W57: 0 | X57: 0 | Y57: EXACT_MATCH
A58: TXN000057 | B58: TXN000057 | C58: 1000 | D58: Cash | E58: 45882 | F58: 141.26 | G58: USD | H58: UK | I58: CC200 | J58: CustB | K58: Refund | L58: BANK-SAV | M58: Bank Savings | N58: 45882 | O58: 141.26 | P58: USD | Q58: UK | R58: CC200 | S58: CustB | T58: Refund | U58: 1000 | V58: TRUE | W58: 0 | X58: 0 | Y58: EXACT_MATCH
A59: TXN000058 | B59: TXN000058 | C59: 4000 | D59: COGS | E59: 45889 | F59: 625.41 | G59: USD | H59: IN | I59: CC200 | J59: CustC | K59: Invoice settlement | L59: COGS-INV | M59: COGS Inventory | N59: 45889 | O59: 625.41 | P59: USD | Q59: IN | R59: CC200 | S59: CustC | T59: Invoice settlement | U59: 4000 | V59: TRUE | W59: 0 | X59: 0 | Y59: EXACT_MATCH
A60: TXN000059 | B60: TXN000059 | C60: 1000 | D60: Cash | E60: 45903 | F60: -476.31 | G60: USD | H60: DE | I60: CC400 | J60: VendX | K60: Refund | L60: BANK-SAV | M60: Bank Savings | N60: 45903 | O60: -476.31 | P60: USD | Q60: DE | R60: CC400 | S60: VendX | T60: Refund | U60: 1000 | V60: TRUE | W60: 0 | X60: 0 | Y60: EXACT_MATCH
A61: TXN000060 | B61: TXN000060 | C61: 1000 | D61: Cash | E61: 45881 | F61: -798.27 | G61: USD | H61: DE | I61: CC100 | J61: CustA | L61: BANK-CHK | M61: Bank Checking | N61: 45881 | O61: -798.27 | P61: USD | Q61: DE | R61: CC100 | S61: CustA | U61: 1000 | V61: TRUE | W61: 0 | X61: 0 | Y61: EXACT_MATCH
A62: TXN000061 | B62: TXN000061 | C62: 3000 | D62: Revenue | E62: 45913 | F62: -407.8 | G62: USD | H62: DE | I62: CC300 | J62: CustA | L62: REV-ONLINE | M62: Revenue Online | N62: 45914 | O62: -406.08 | P62: USD | Q62: DE | R62: CC300 | S62: CustA | U62: 3000 | V62: TRUE | W62: -1.72 | X62: -1 | Y62: MISMATCH
A63: TXN000062 | B63: TXN000062 | C63: 1100 | D63: Accounts Receivable | E63: 45874 | F63: 23.41 | G63: USD | H63: IN | I63: CC300 | J63: VendX | K63: Adjustment | L63: AR-CUST | M63: Subledger AR | N63: 45874 | O63: 23.41 | P63: USD | Q63: IN | R63: CC300 | S63: VendX | T63: Adjustment | U63: 1100 | V63: TRUE | W63: 0 | X63: 0 | Y63: EXACT_MATCH
A64: TXN000063 | B64: TXN000063 | C64: 5000 | D64: Operating Expense | E64: 45915 | F64: 475.1 | G64: USD | H64: IN | I64: CC300 | J64: CustA | K64: Invoice settlement | L64: OPEX-IT | M64: Operating IT | N64: 45915 | O64: 475.1 | P64: USD | Q64: IN | R64: CC300 | S64: CustA | T64: Invoice settlement | U64: 5000 | V64: TRUE | W64: 0 | X64: 0 | Y64: EXACT_MATCH
A65: TXN000064 | B65: TXN000064 | C65: 1000 | D65: Cash | E65: 45908 | F65: 924.88 | G65: USD | H65: IN | I65: CC100 | J65: CustC | K65: Monthly activity | L65: BANK-CHK | M65: Bank Checking | N65: 45908 | O65: 924.51 | P65: USD | Q65: IN | R65: CC100 | S65: CustC | T65: Monthly activity | U65: 1000 | V65: TRUE | W65: 0.37 | X65: 0 | Y65: NEAR_MATCH
A66: TXN000065 | B66: TXN000065 | C66: 1000 | D66: Cash | E66: 45908 | F66: -404.14 | G66: USD | H66: UK | I66: CC100 | J66: CustC | L66: BANK-SAV | M66: Bank Savings | N66: 45908 | O66: -404.14 | P66: USD | Q66: UK | R66: CC100 | S66: CustC | U66: 1000 | V66: TRUE | W66: 0 | X66: 0 | Y66: EXACT_MATCH
A67: TXN000066 | B67: TXN000066 | C67: 1000 | D67: Cash | E67: 45886 | F67: -277.54 | G67: USD | H67: IN | I67: CC300 | J67: VendY | K67: Adjustment | L67: BANK-SAV | M67: Bank Savings | N67: 45888 | O67: -272.59 | P67: USD | Q67: IN | R67: CC300 | S67: VendY | T67: Adjustment | U67: 1000 | V67: TRUE | W67: -4.95 | X67: -2 | Y67: MISMATCH
A68: TXN000067 | B68: TXN000067 | C68: 1000 | D68: Cash | E68: 45890 | F68: 201.6 | G68: USD | H68: US | I68: CC200 | J68: CustC | K68: Monthly activity | L68: BANK-CHK | M68: Bank Checking | N68: 45890 | O68: 201.6 | P68: USD | Q68: US | R68: CC200 | S68: CustC | T68: Monthly activity | U68: 1000 | V68: TRUE | W68: 0 | X68: 0 | Y68: EXACT_MATCH
A69: TXN000068 | B69: TXN000068 | C69: 1100 | D69: Accounts Receivable | E69: 45869 | F69: 237.5 | G69: USD | H69: DE | I69: CC200 | J69: CustC | K69: Card fees | L69: AR-CUST | M69: Subledger AR | N69: 45869 | O69: 237.5 | P69: USD | Q69: DE | R69: CC200 | S69: CustC | T69: Card fees | U69: 1100 | V69: TRUE | W69: 0 | X69: 0 | Y69: EXACT_MATCH
A70: TXN000069 | B70: TXN000069 | C70: 5000 | D70: Operating Expense | E70: 45900 | F70: -424.95 | G70: USD | H70: DE | I70: CC100 | J70: CustC | K70: Monthly activity | L70: OPEX-IT | M70: Operating IT | N70: 45900 | O70: -424.95 | P70: USD | Q70: DE | R70: CC100 | S70: CustC | T70: Monthly activity | U70: 5000 | V70: TRUE | W70: 0 | X70: 0 | Y70: EXACT_MATCH
A71: TXN000070 | B71: TXN000070 | C71: 1000 | D71: Cash | E71: 45858 | F71: 205 | G71: USD | H71: UK | I71: CC400 | J71: CustB | K71: Card fees | L71: BANK-CHK | M71: Bank Checking | N71: 45858 | O71: 205.18 | P71: USD | Q71: UK | R71: CC400 | S71: CustB | T71: Card fees | U71: 1000 | V71: TRUE | W71: -0.18 | X71: 0 | Y71: NEAR_MATCH
A72: TXN000071 | B72: TXN000071 | C72: 1000 | D72: Cash | E72: 45899 | F72: 874.41 | G72: USD | H72: IN | I72: CC400 | J72: VendY | L72: BANK-SAV | M72: Bank Savings | N72: 45899 | O72: 874.41 | P72: USD | Q72: IN | R72: CC400 | S72: VendY | U72: 1000 | V72: TRUE | W72: 0 | X72: 0 | Y72: EXACT_MATCH
A73: TXN000072 | B73: TXN000072 | C73: 4000 | D73: COGS | E73: 45889 | F73: -429.34 | G73: USD | H73: UK | I73: CC200 | J73: CustC | K73: Adjustment | L73: COGS-INV | M73: COGS Inventory | N73: 45889 | O73: -429.34 | P73: USD | Q73: UK | R73: CC200 | S73: CustC | T73: Adjustment | U73: 4000 | V73: TRUE | W73: 0 | X73: 0 | Y73: EXACT_MATCH
A74: TXN000073 | B74: TXN000073 | C74: 1100 | D74: Accounts Receivable | E74: 45882 | F74: 527.16 | G74: USD | H74: US | I74: CC200 | J74: CustA | K74: Monthly activity | L74: AR-CUST | M74: Subledger AR | N74: 45882 | O74: 527.16 | P74: USD | Q74: US | R74: CC200 | S74: CustA | T74: Monthly activity | U74: 1100 | V74: TRUE | W74: 0 | X74: 0 | Y74: EXACT_MATCH
A75: TXN000074 | B75: TXN000074 | C75: 3000 | D75: Revenue | E75: 45884 | F75: -859.56 | G75: USD | H75: US | I75: CC400 | K75: Subscription | L75: REV-RETAIL | M75: Revenue Retail | N75: 45884 | O75: -859.56 | P75: USD | Q75: US | R75: CC400 | T75: Subscription | U75: 3000 | V75: TRUE | W75: 0 | X75: 0 | Y75: EXACT_MATCH
A76: TXN000075 | B76: TXN000075 | C76: 3000 | D76: Revenue | E76: 45895 | F76: -875.83 | G76: USD | H76: DE | I76: CC100 | J76: VendX | K76: Adjustment | L76: REV-RETAIL | M76: Revenue Retail | N76: 45895 | O76: -875.83 | P76: USD | Q76: DE | R76: CC100 | S76: VendX | T76: Adjustment | U76: 3000 | V76: TRUE | W76: 0 | X76: 0 | Y76: EXACT_MATCH
A77: TXN000076 | B77: TXN000076 | C77: 1100 | D77: Accounts Receivable | E77: 45874 | F77: 446.82 | G77: USD | H77: DE | I77: CC300 | J77: CustC | K77: Subscription | L77: AR-CUST | M77: Subledger AR | N77: 45874 | O77: 446.82 | P77: USD | Q77: DE | R77: CC300 | S77: CustC | T77: Subscription | U77: 1100 | V77: TRUE | W77: 0 | X77: 0 | Y77: EXACT_MATCH
A78: TXN000077 | B78: TXN000077 | C78: 2000 | D78: Accounts Payable | E78: 45872 | F78: -582.99 | G78: USD | H78: DE | I78: CC200 | J78: CustC | K78: Adjustment | L78: AP-VENDOR | M78: Subledger AP | N78: 45874 | O78: -582.61 | P78: USD | Q78: DE | R78: CC200 | S78: CustC | T78: Adjustment | U78: 2000 | V78: TRUE | W78: -0.38 | X78: -2 | Y78: NEAR_MATCH
A79: TXN000078 | B79: TXN000078 | C79: 1000 | D79: Cash | E79: 45878 | F79: -683.76 | G79: USD | H79: IN | I79: CC300 | J79: VendY | K79: Refund | L79: BANK-CHK | M79: Bank Checking | N79: 45878 | O79: -683.76 | P79: USD | Q79: IN | R79: CC300 | S79: VendY | T79: Refund | U79: 1000 | V79: TRUE | W79: 0 | X79: 0 | Y79: EXACT_MATCH
A80: TXN000079 | B80: TXN000079 | C80: 3000 | D80: Revenue | E80: 45872 | F80: 451.79 | G80: USD | H80: US | I80: CC100 | J80: CustC | L80: REV-ONLINE | M80: Revenue Online | N80: 45872 | O80: 451.79 | P80: USD | Q80: US | R80: CC100 | S80: CustC | U80: 3000 | V80: TRUE | W80: 0 | X80: 0 | Y80: EXACT_MATCH
A81: TXN000080 | B81: TXN000080 | C81: 1000 | D81: Cash | E81: 45866 | F81: -55.5 | G81: USD | H81: US | I81: CC400 | J81: CustA | K81: Invoice settlement | L81: BANK-SAV | M81: Bank Savings | N81: 45867 | O81: -46.61 | P81: USD | Q81: US | R81: CC400 | S81: CustA | T81: Invoice settlement | U81: 1000 | V81: TRUE | W81: -8.89 | X81: -1 | Y81: MISMATCH
A82: TXN000081 | B82: TXN000081 | C82: 3000 | D82: Revenue | E82: 45897 | F82: -663.68 | G82: USD | H82: UK | I82: CC400 | K82: Invoice settlement | L82: REV-RETAIL | M82: Revenue Retail | N82: 45897 | O82: -663.68 | P82: USD | Q82: UK | R82: CC400 | T82: Invoice settlement | U82: 3000 | V82: TRUE | W82: 0 | X82: 0 | Y82: EXACT_MATCH
A83: TXN000082 | B83: TXN000082 | C83: 5000 | D83: Operating Expense | E83: 45866 | F83: -723.59 | G83: USD | H83: UK | I83: CC100 | L83: OPEX-MKT | M83: Operating Marketing | N83: 45869 | O83: -719.22 | P83: USD | Q83: UK | R83: CC100 | U83: 5000 | V83: TRUE | W83: -4.37 | X83: -3 | Y83: MISMATCH
A84: TXN000083 | B84: TXN000083 | C84: 5000 | D84: Operating Expense | E84: 45897 | F84: 603.88 | G84: USD | H84: UK | I84: CC100 | K84: Refund | L84: OPEX-IT | M84: Operating IT | N84: 45897 | O84: 603.18 | P84: USD | Q84: UK | R84: CC100 | T84: Refund | U84: 5000 | V84: TRUE | W84: 0.7 | X84: 0 | Y84: NEAR_MATCH
A85: TXN000084 | B85: TXN000084 | C85: 6000 | D85: Other Income | E85: 45908 | F85: 269.11 | G85: USD | H85: UK | I85: CC100 | J85: CustA | K85: Monthly activity | L85: MISC-INC | M85: Misc Income | N85: 45908 | O85: 269.11 | P85: USD | Q85: UK | R85: CC100 | S85: CustA | T85: Monthly activity | U85: 6000 | V85: TRUE | W85: 0 | X85: 0 | Y85: EXACT_MATCH
A86: TXN000085 | B86: TXN000085 | C86: 1100 | D86: Accounts Receivable | E86: 45897 | F86: -450.99 | G86: USD | H86: US | I86: CC400 | K86: Card fees | L86: AR-CUST | M86: Subledger AR | N86: 45897 | O86: -450.99 | P86: USD | Q86: US | R86: CC400 | T86: Card fees | U86: 1100 | V86: TRUE | W86: 0 | X86: 0 | Y86: EXACT_MATCH
A87: TXN000086 | B87: TXN000086 | C87: 5000 | D87: Operating Expense | E87: 45860 | F87: 352.31 | G87: USD | H87: UK | I87: CC400 | J87: CustC | K87: Monthly activity | L87: OPEX-IT | M87: Operating IT | N87: 45860 | O87: 352.31 | P87: USD | Q87: UK | R87: CC400 | S87: CustC | T87: Monthly activity | U87: 5000 | V87: TRUE | W87: 0 | X87: 0 | Y87: EXACT_MATCH
A88: TXN000087 | B88: TXN000087 | C88: 5000 | D88: Operating Expense | E88: 45908 | F88: -425.07 | G88: USD | H88: US | I88: CC100 | J88: VendZ | K88: Refund | L88: OPEX-MKT | M88: Operating Marketing | N88: 45908 | O88: -425.07 | P88: USD | Q88: US | R88: CC100 | S88: VendZ | T88: Refund | U88: 5000 | V88: TRUE | W88: 0 | X88: 0 | Y88: EXACT_MATCH
A89: TXN000088 | B89: TXN000088 | C89: 5000 | D89: Operating Expense | E89: 45873 | F89: 824.22 | G89: USD | H89: DE | I89: CC200 | J89: VendZ | L89: OPEX-MKT | M89: Operating Marketing | N89: 45873 | O89: 824.22 | P89: USD | Q89: DE | R89: CC200 | S89: VendZ | U89: 5000 | V89: TRUE | W89: 0 | X89: 0 | Y89: EXACT_MATCH
A90: TXN000089 | B90: TXN000089 | C90: 3000 | D90: Revenue | E90: 45871 | F90: 882.39 | G90: USD | H90: IN | I90: CC400 | K90: Card fees | L90: REV-ONLINE | M90: Revenue Online | N90: 45871 | O90: 882.39 | P90: USD | Q90: IN | R90: CC400 | T90: Card fees | U90: 3000 | V90: TRUE | W90: 0 | X90: 0 | Y90: EXACT_MATCH
A91: TXN000090 | B91: TXN000090 | C91: 1000 | D91: Cash | E91: 45887 | F91: 667.35 | G91: USD | H91: DE | I91: CC100 | J91: VendY | K91: Refund | L91: BANK-SAV | M91: Bank Savings | N91: 45887 | O91: 667.35 | P91: USD | Q91: DE | R91: CC100 | S91: VendY | T91: Refund | U91: 1000 | V91: TRUE | W91: 0 | X91: 0 | Y91: EXACT_MATCH
A92: TXN000091 | B92: TXN000091 | C92: 3000 | D92: Revenue | E92: 45861 | F92: 637.19 | G92: USD | H92: DE | I92: CC300 | J92: VendZ | K92: Refund | L92: REV-ONLINE | M92: Revenue Online | N92: 45863 | O92: 637.55 | P92: USD | Q92: DE | R92: CC300 | S92: VendZ | T92: Refund | U92: 3000 | V92: TRUE | W92: -0.36 | X92: -2 | Y92: NEAR_MATCH
A93: TXN000092 | B93: TXN000092 | C93: 3000 | D93: Revenue | E93: 45896 | F93: 669.16 | G93: USD | H93: US | I93: CC400 | J93: CustA | K93: Card fees | L93: REV-RETAIL | M93: Revenue Retail | N93: 45896 | O93: 669.16 | P93: USD | Q93: US | R93: CC400 | S93: CustA | T93: Card fees | U93: 3000 | V93: TRUE | W93: 0 | X93: 0 | Y93: EXACT_MATCH
A94: TXN000093 | B94: TXN000093 | C94: 3000 | D94: Revenue | E94: 45900 | F94: -496.94 | G94: USD | H94: UK | I94: CC400 | J94: CustC | K94: Refund | L94: REV-RETAIL | M94: Revenue Retail | N94: 45899 | O94: -496.97 | P94: USD | Q94: UK | R94: CC400 | S94: CustC | T94: Refund | U94: 3000 | V94: TRUE | W94: 0.03 | X94: 1 | Y94: NEAR_MATCH
A95: TXN000094 | B95: TXN000094 | C95: 5000 | D95: Operating Expense | E95: 45875 | F95: 481.08 | G95: USD | H95: IN | I95: CC100 | J95: VendY | K95: Adjustment | L95: OPEX-IT | M95: Operating IT | N95: 45877 | O95: 480.1 | P95: USD | Q95: IN | R95: CC100 | S95: VendY | T95: Adjustment | U95: 5000 | V95: TRUE | W95: 0.98 | X95: -2 | Y95: NEAR_MATCH
A96: TXN000095 | B96: TXN000095 | C96: 3000 | D96: Revenue | E96: 45862 | F96: 331.59 | G96: USD | H96: US | I96: CC300 | J96: VendX | K96: Monthly activity | L96: REV-RETAIL | M96: Revenue Retail | N96: 45860 | O96: 344.27 | P96: USD | Q96: US | R96: CC300 | S96: VendX | T96: Monthly activity | U96: 3000 | V96: TRUE | W96: -12.68 | X96: 2 | Y96: MISMATCH
A97: TXN000096 | B97: TXN000096 | C97: 5000 | D97: Operating Expense | E97: 45885 | F97: 486.03 | G97: USD | H97: IN | I97: CC200 | J97: CustB | K97: Monthly activity | L97: OPEX-IT | M97: Operating IT | N97: 45885 | O97: 486.03 | P97: USD | Q97: IN | R97: CC200 | S97: CustB | T97: Monthly activity | U97: 5000 | V97: TRUE | W97: 0 | X97: 0 | Y97: EXACT_MATCH
A98: TXN000097 | B98: TXN000097 | C98: 6000 | D98: Other Income | E98: 45862 | F98: -1064.99 | G98: USD | H98: DE | I98: CC300 | J98: CustB | K98: Subscription | L98: MISC-INC | M98: Misc Income | N98: 45862 | O98: -1064.99 | P98: USD | Q98: DE | R98: CC300 | S98: CustB | T98: Subscription | U98: 6000 | V98: TRUE | W98: 0 | X98: 0 | Y98: EXACT_MATCH
A99: TXN000098 | B99: TXN000098 | C99: 5000 | D99: Operating Expense | E99: 45874 | F99: 717.26 | G99: USD | H99: DE | I99: CC200 | J99: VendX | K99: Card fees | L99: OPEX-IT | M99: Operating IT | N99: 45874 | O99: 717.26 | P99: USD | Q99: DE | R99: CC200 | S99: VendX | T99: Card fees | U99: 5000 | V99: TRUE | W99: 0 | X99: 0 | Y99: EXACT_MATCH
A100: TXN000099 | B100: TXN000099 | C100: 4000 | D100: COGS | E100: 45858 | F100: -414.47 | G100: USD | H100: IN | I100: CC400 | J100: VendX | K100: Invoice settlement | L100: COGS-INV | M100: COGS Inventory | N100: 45861 | O100: -403.37 | P100: USD | Q100: IN | R100: CC400 | S100: VendX | T100: Invoice settlement | U100: 4000 | V100: TRUE | W100: -11.1 | X100: -3 | Y100: MISMATCH
...

Sheet Lists
A1: GL_Accounts | B1: Source_Accounts
A2: 1000 | B2: AP-VENDOR
A3: 1100 | B3: AR-CUST
A4: 1200 | B4: BANK-CHK
A5: 2000 | B5: BANK-SAV
A6: 2100 | B6: COGS-INV
A7: 3000 | B7: MISC-INC
A8: 4000 | B8: OPEX-IT
A9: 5000 | B9: OPEX-MKT
A10: 6000 | B10: REV-ONLINE
A11: 7000 | B11: REV-RETAIL

Sheet Missing_Map
A1: source_account | B1: source_account_name | C1: ref_id | D1: txn_date | E1: amount_B | F1: currency | G1: entity | H1: cost_center | I1: counterparty | J1: description

Sheet MissingMap_BySource
A1: source_account | B1: missing_map_count
